Workbook

Sheet Hướng dẫn
A1: BÁO CÁO KIỂM THỬ – PHẦN MỀM QUẢN LÝ PHÒNG KHÁM THÚ CƯNG (PET CLINIC)
A2: File tổng hợp test case, kết quả thực thi và danh sách lỗi. Đọc sheet này trước.
A4: Sheet | B4: Nội dung | C4: Cách đọc
A5: Tổng quan | B5: Thông tin dự án, môi trường, bảng thống kê Pass/Fail, lỗi theo mức độ | C5: Các con số được tính tự động bằng công thức từ các sheet bên dưới
A6: TC chức năng | B6: 74 test case kiểm thử chức năng trên giao diện (chạy tự động bằng Selenium) | C6: Mỗi dòng 1 test case: các bước, dữ liệu nhập, kết quả mong đợi, kết quả thực tế, trạng thái
A7: Unit test | B7: 30 unit test kiểm tra mã nguồn bên trong (schema dữ liệu, lớp nghiệp vụ) | C7: Cột “Đối tượng được test” cho biết hàm/schema nào trong mã nguồn
A8: TC phi chức năng | B8: 28 test case: tải, chịu tải, toàn vẹn dữ liệu, độ tin cậy và phục hồi | C8: Cột “Kết quả đo được” là số liệu thật đo bằng autocannon / Mocha
A9: Danh sách lỗi | B9: Lỗi phát hiện, mức độ nghiêm trọng, bước tái hiện, vị trí nghi vấn trong mã nguồn | C9: Mã lỗi BUG-xxx được ghi ngược lại ở cột “Mã lỗi” của sheet test case
A11: Trạng thái
A12: Pass | B12: Kết quả thực tế đúng như kết quả mong đợi
A13: Fail | B13: Kết quả thực tế khác kết quả mong đợi → có lỗi, xem sheet Danh sách lỗi
A14: Blocked | B14: Không thực hiện được do bị chặn bởi lỗi khác / thiếu môi trường
A15: Not Run | B15: Chưa thực hiện
A17: Mức độ lỗi
A18: Cao | B18: Chức năng chính không dùng được, mất/sai dữ liệu, lỗ hổng bảo mật
A19: Trung bình | B19: Vi phạm quy tắc nghiệp vụ nhưng vẫn thao tác được
A20: Thấp | B20: Thông báo thiếu/khó hiểu, lỗi hiển thị
A22: Cập nhật kết quả | B22: Khi kiểm thử lại: sửa cột Trạng thái (chọn trong danh sách) và Kết quả thực tế; sheet Tổng quan tự cập nhật.

Sheet Tổng quan
A1: TỔNG QUAN KẾT QUẢ KIỂM THỬ
A2: Các ô số liệu là công thức – tự cập nhật khi sửa Trạng thái ở các sheet test case.
A4: Phần mềm | B4: Pet Clinic Pro – quản lý phòng khám thú cưng (React + Express + MySQL)
A5: Phiên bản kiểm thử | B5: 1.0.0 (MySQL Edition), bản build production
A6: Môi trường | B6: Windows 10/11; Microsoft Edge (headless 1440×900); Node.js 20+; MySQL 8.x – CSDL kiểm thử riêng
A7: Dữ liệu mẫu | B7: 12 bác sĩ, 30 khách hàng, 50 thú cưng, 30 vật tư, 60 lịch hẹn, 43 hồ sơ khám, 15 camera, 31 ca trực, 60 hóa đơn
A8: Công cụ | B8: Mocha, Selenium WebDriver, tsx, autocannon, mysql2
A9: Thời gian thực hiện | B9: 02/10/2026 – 03/10/2026
A10: Người thực hiện | B10: Nhóm kiểm thử
A12: 1. Kết quả theo loại kiểm thử
A13: Loại kiểm thử | B13: Tổng | C13: Pass | D13: Fail | E13: Chưa chạy / Blocked | F13: Tỷ lệ Pass
A14: Kiểm thử chức năng (giao diện) | B14: =COUNTA('TC chức năng'!B5:B78) | C14: =COUNTIF('TC chức năng'!K5:K78,"Pass") | D14: =COUNTIF('TC chức năng'!K5:K78,"Fail") | E14: =B14-C14-D14 | F14: =IF(B14=0,0,C14/B14)
A15: Kiểm thử đơn vị (Unit test) | B15: =COUNTA('Unit test'!B5:B34) | C15: =COUNTIF('Unit test'!G5:G34,"Pass") | D15: =COUNTIF('Unit test'!G5:G34,"Fail") | E15: =B15-C15-D15 | F15: =IF(B15=0,0,C15/B15)
A16: Kiểm thử phi chức năng | B16: =COUNTA('TC phi chức năng'!B5:B32) | C16: =COUNTIF('TC phi chức năng'!I5:I32,"Pass") | D16: =COUNTIF('TC phi chức năng'!I5:I32,"Fail") | E16: =B16-C16-D16 | F16: =IF(B16=0,0,C16/B16)
A17: TỔNG CỘNG | B17: =SUM(B14:B16) | C17: =SUM(C14:C16) | D17: =SUM(D14:D16) | E17: =SUM(E14:E16) | F17: =IF(B17=0,0,C17/B17)
A19: 2. Kiểm thử chức năng theo tác nhân
A20: Tác nhân | B20: Tổng | C20: Pass | D20: Fail | F20: Tỷ lệ Pass
A21: HỆ THỐNG | B21: =COUNTIF('TC chức năng'!C5:C78,A21) | C21: =COUNTIFS('TC chức năng'!C5:C78,A21,'TC chức năng'!K5:K78,"Pass") | D21: =COUNTIFS('TC chức năng'!C5:C78,A21,'TC chức năng'!K5:K78,"Fail") | F21: =IF(B21=0,0,C21/B21)
A22: LỄ TÂN | B22: =COUNTIF('TC chức năng'!C5:C78,A22) | C22: =COUNTIFS('TC chức năng'!C5:C78,A22,'TC chức năng'!K5:K78,"Pass") | D22: =COUNTIFS('TC chức năng'!C5:C78,A22,'TC chức năng'!K5:K78,"Fail") | F22: =IF(B22=0,0,C22/B22)
A23: BÁC SĨ | B23: =COUNTIF('TC chức năng'!C5:C78,A23) | C23: =COUNTIFS('TC chức năng'!C5:C78,A23,'TC chức năng'!K5:K78,"Pass") | D23: =COUNTIFS('TC chức năng'!C5:C78,A23,'TC chức năng'!K5:K78,"Fail") | F23: =IF(B23=0,0,C23/B23)
A24: QUẢN TRỊ VIÊN / KẾ TOÁN | B24: =COUNTIF('TC chức năng'!C5:C78,A24) | C24: =COUNTIFS('TC chức năng'!C5:C78,A24,'TC chức năng'!K5:K78,"Pass") | D24: =COUNTIFS('TC chức năng'!C5:C78,A24,'TC chức năng'!K5:K78,"Fail") | F24: =IF(B24=0,0,C24/B24)
A26: 3. Kiểm thử phi chức năng theo loại
A27: Loại | B27: Tổng | C27: Pass | D27: Fail | F27: Tỷ lệ Pass
A28: Tải & hiệu năng | B28: =COUNTIF('TC phi chức năng'!C5:C32,A28) | C28: =COUNTIFS('TC phi chức năng'!C5:C32,A28,'TC phi chức năng'!I5:I32,"Pass") | D28: =COUNTIFS('TC phi chức năng'!C5:C32,A28,'TC phi chức năng'!I5:I32,"Fail") | F28: =IF(B28=0,0,C28/B28)
A29: Chịu tải | B29: =COUNTIF('TC phi chức năng'!C5:C32,A29) | C29: =COUNTIFS('TC phi chức năng'!C5:C32,A29,'TC phi chức năng'!I5:I32,"Pass") | D29: =COUNTIFS('TC phi chức năng'!C5:C32,A29,'TC phi chức năng'!I5:I32,"Fail") | F29: =IF(B29=0,0,C29/B29)
A30: Toàn vẹn dữ liệu | B30: =COUNTIF('TC phi chức năng'!C5:C32,A30) | C30: =COUNTIFS('TC phi chức năng'!C5:C32,A30,'TC phi chức năng'!I5:I32,"Pass") | D30: =COUNTIFS('TC phi chức năng'!C5:C32,A30,'TC phi chức năng'!I5:I32,"Fail") | F30: =IF(B30=0,0,C30/B30)
A31: Tin cậy & phục hồi | B31: =COUNTIF('TC phi chức năng'!C5:C32,A31) | C31: =COUNTIFS('TC phi chức năng'!C5:C32,A31,'TC phi chức năng'!I5:I32,"Pass") | D31: =COUNTIFS('TC phi chức năng'!C5:C32,A31,'TC phi chức năng'!I5:I32,"Fail") | F31: =IF(B31=0,0,C31/B31)
A33: 4. Lỗi theo mức độ nghiêm trọng
A34: Mức độ | B34: Số lỗi | C34: Chưa đóng
A35: Cao | B35: =COUNTIF('Danh sách lỗi'!E5:E28,A35) | C35: =COUNTIFS('Danh sách lỗi'!E5:E28,A35,'Danh sách lỗi'!K5:K28,"<>Đóng (Closed)")
A36: Trung bình | B36: =COUNTIF('Danh sách lỗi'!E5:E28,A36) | C36: =COUNTIFS('Danh sách lỗi'!E5:E28,A36,'Danh sách lỗi'!K5:K28,"<>Đóng (Closed)")
A37: Thấp | B37: =COUNTIF('Danh sách lỗi'!E5:E28,A37) | C37: =COUNTIFS('Danh sách lỗi'!E5:E28,A37,'Danh sách lỗi'!K5:K28,"<>Đóng (Closed)")
A38: Tổng số lỗi | B38: =SUM(B35:B37) | C38: =SUM(C35:C37)
A40: 5. Kết luận
A41: =IF(AND(F14>=0.9,B35=0),"ĐẠT điều kiện chấp thuận","CHƯA ĐẠT điều kiện chấp thuận (cần ≥ 90% Pass chức năng và không còn lỗi mức Cao)")
A42: Ghi chú: số liệu hiệu năng đo khi máy sinh tải và máy chủ chạy chung một máy – mang tính tham khảo.

Sheet TC chức năng
A1: TEST CASE KIỂM THỬ CHỨC NĂNG
A2: Công cụ: Mocha + Selenium WebDriver (Microsoft Edge, headless). Dữ liệu mẫu nạp lại trước khi chạy.
A4: STT | B4: Test Case ID | C4: Tác nhân | D4: Chức năng (Use Case) | E4: Mô tả test case | F4: Điều kiện trước | G4: Các bước thực hiện → kết quả từng bước | H4: Dữ liệu đầu vào | I4: Kết quả mong đợi | J4: Kết quả thực tế | K4: Trạng thái | L4: Mức độ lỗi | M4: Mã lỗi | N4: Người test | O4: Ngày test
A5: 1 | B5: SYS-TC001 | C5: HỆ THỐNG | D5: Truy cập hệ thống & trang Tổng quan | E5: Truy cập trang chủ của hệ thống | F5: Ứng dụng đang chạy; dữ liệu mẫu đã nạp | G5: 1. Mở trình duyệt, truy cập địa chỉ hệ thống → Trang web được truy cập 2. Quan sát trang Tổng quan → Hiển thị tiêu đề và 6 thẻ thống kê | H5: http://localhost:5000 | I5: Trang "Tổng quan vận hành phòng khám" hiển thị đủ 6 thẻ thống kê | J5: Trang Tổng quan hiển thị đầy đủ 6 thẻ thống kê | K5: Pass | N5: Nhóm kiểm thử | O5: 03/10/2026
A6: 2 | B6: SYS-TC002 | C6: HỆ THỐNG | D6: Truy cập hệ thống & trang Tổng quan | E6: Điều hướng tới các chức năng qua thanh menu bên trái | F6: Ứng dụng đang chạy; dữ liệu mẫu đã nạp | G6: 1. Truy cập trang chủ → Trang Tổng quan được hiển thị 2. Lần lượt chọn từng mục trên menu → Trang tương ứng được hiển thị | H6: Bác sĩ, Khách hàng, Lịch hẹn, Hồ sơ khám, Ca bác sĩ, Kho thuốc, Hóa đơn, Camera giám sát | I6: Mỗi mục menu mở đúng trang chức năng tương ứng | J6: Cả 8 mục menu mở đúng trang | K6: Pass | N6: Nhóm kiểm thử | O6: 03/10/2026
A7: 3 | B7: SYS-TC003 | C7: HỆ THỐNG | D7: Truy cập hệ thống & trang Tổng quan | E7: Truy cập đường dẫn không tồn tại | F7: Ứng dụng đang chạy; dữ liệu mẫu đã nạp | G7: 1. Nhập đường dẫn không tồn tại trên thanh địa chỉ → Hệ thống xử lý đường dẫn | H7: /trang-khong-ton-tai | I7: Hiển thị trang "404 - Không tìm thấy trang" | J7: Hiển thị trang 404 | K7: Pass | N7: Nhóm kiểm thử | O7: 03/10/2026
A8: 4 | B8: SYS-TC004 | C8: HỆ THỐNG | D8: Đăng nhập & phân quyền (RBAC – R6.2) | E8: Truy cập chức năng quản lý khi chưa đăng nhập | F8: Ứng dụng đang chạy; dữ liệu mẫu đã nạp | G8: 1. Mở trình duyệt mới (chưa đăng nhập) → Không có phiên đăng nhập 2. Truy cập trực tiếp trang Khách hàng → Hệ thống chuyển tới trang đăng nhập | H8: /customers | I8: Hệ thống yêu cầu đăng nhập, không cho xem dữ liệu khách hàng | J8: Không có trang đăng nhập – truy cập thẳng được danh sách khách hàng | K8: Fail | L8: Cao | M8: BUG-001 | N8: Nhóm kiểm thử | O8: 03/10/2026
A9: 5 | B9: SYS-TC005 | C9: HỆ THỐNG | D9: Truy cập hệ thống & trang Tổng quan | E9: Chuyển đổi giao diện sáng/tối | F9: Ứng dụng đang chạy; dữ liệu mẫu đã nạp | G9: 1. Truy cập trang chủ → Giao diện sáng 2. Nhấn nút đổi giao diện ở góc phải → Giao diện chuyển sang tối 3. Nhấn lại nút → Giao diện trở lại sáng | I9: Giao diện chuyển đổi qua lại giữa sáng và tối | J9: Giao diện đổi sáng ↔ tối đúng | K9: Pass | N9: Nhóm kiểm thử | O9: 03/10/2026
A10: 6 | B10: UC1.1-TC001 | C10: LỄ TÂN | D10: UC1.1 Tạo mới hồ sơ khách hàng | E10: Bỏ trống tất cả các trường và nhấn "Lưu khách hàng" | F10: Ứng dụng đang chạy; dữ liệu mẫu đã nạp | G10: 1. Chọn "Thêm khách hàng" → Form thêm khách hàng hiển thị 2. Bỏ trống Họ tên, Email, SĐT 3. Nhấn "Lưu khách hàng" → Hiển thị thông báo lỗi | I10: Hiển thị lỗi "Họ tên là bắt buộc", "Email không hợp lệ", "Số điện thoại phải gồm đúng 10 chữ số" | J10: Hiển thị đủ 3 thông báo lỗi, không lưu dữ liệu | K10: Pass | N10: Nhóm kiểm thử | O10: 03/10/2026
A11: 7 | B11: UC1.1-TC002 | C11: LỄ TÂN | D11: UC1.1 Tạo mới hồ sơ khách hàng | E11: Bỏ trống Họ tên, các trường khác hợp lệ | F11: Ứng dụng đang chạy; dữ liệu mẫu đã nạp | G11: 1. Chọn "Thêm khách hàng" → Form hiển thị 2. Bỏ trống Họ tên 3. Nhập Email, SĐT hợp lệ 4. Nhấn "Lưu khách hàng" → Hiển thị thông báo lỗi | H11: a@test.vn / 0987654321 | I11: Hiển thị lỗi "Họ tên là bắt buộc" | J11: Hiển thị "Họ tên là bắt buộc" | K11: Pass | N11: Nhóm kiểm thử | O11: 03/10/2026
A12: 8 | B12: UC1.1-TC003 | C12: LỄ TÂN | D12: UC1.1 Tạo mới hồ sơ khách hàng | E12: Email sai định dạng | F12: Ứng dụng đang chạy; dữ liệu mẫu đã nạp | G12: 1. Chọn "Thêm khách hàng" → Form hiển thị 2. Nhập Họ tên, SĐT hợp lệ 3. Nhập Email sai định dạng 4. Nhấn "Lưu khách hàng" → Hiển thị thông báo lỗi | H12: Lê Minh / 0987654321 leminh.gmail.com | I12: Hiển thị thông báo email không hợp lệ, không lưu khách hàng | J12: Form không được gửi, trình duyệt báo: "Vui lòng bao gồm '@' trong địa chỉ email. 'leminh.gmail.com' đang thiếu một '@'." | K12: Pass | N12: Nhóm kiểm thử | O12: 03/10/2026
A13: 9 | B13: UC1.1-TC004 | C13: LỄ TÂN | D13: UC1.1 Tạo mới hồ sơ khách hàng | E13: Kiểm thử giá trị biên: SĐT 9 chữ số | F13: Ứng dụng đang chạy; dữ liệu mẫu đã nạp | G13: 1. Chọn "Thêm khách hàng" → Form hiển thị 2. Nhập Họ tên, Email hợp lệ 3. Nhập SĐT 9 chữ số 4. Nhấn "Lưu khách hàng" → Hiển thị thông báo lỗi | H13: Lê Minh / leminh@test.vn 098765432 | I13: Hiển thị lỗi "Số điện thoại phải gồm đúng 10 chữ số" | J13: Hiển thị lỗi SĐT | K13: Pass | N13: Nhóm kiểm thử | O13: 03/10/2026
A14: 10 | B14: UC1.1-TC005 | C14: LỄ TÂN | D14: UC1.1 Tạo mới hồ sơ khách hàng | E14: Kiểm thử giá trị biên: SĐT 11 chữ số | F14: Ứng dụng đang chạy; dữ liệu mẫu đã nạp | G14: 1. Chọn "Thêm khách hàng" → Form hiển thị 2. Nhập Họ tên, Email hợp lệ 3. Nhập SĐT 11 chữ số 4. Nhấn "Lưu khách hàng" → Hiển thị thông báo lỗi | H14: Lê Minh / leminh@test.vn 09876543210 | I14: Hiển thị lỗi "Số điện thoại phải gồm đúng 10 chữ số" | J14: Hiển thị lỗi SĐT | K14: Pass | N14: Nhóm kiểm thử | O14: 03/10/2026
A15: 11 | B15: UC1.1-TC006 | C15: LỄ TÂN | D15: UC1.1 Tạo mới hồ sơ khách hàng | E15: SĐT chứa ký tự chữ | F15: Ứng dụng đang chạy; dữ liệu mẫu đã nạp | G15: 1. Chọn "Thêm khách hàng" → Form hiển thị 2. Nhập Họ tên, Email hợp lệ 3. Nhập SĐT có chữ 4. Nhấn "Lưu khách hàng" → Hiển thị thông báo lỗi | H15: Lê Minh / leminh@test.vn 09ab123456 | I15: Hiển thị lỗi "Số điện thoại phải gồm đúng 10 chữ số" | J15: Hiển thị lỗi SĐT | K15: Pass | N15: Nhóm kiểm thử | O15: 03/10/2026
A16: 12 | B16: UC1.1-TC007 | C16: LỄ TÂN | D16: UC1.1 Tạo mới hồ sơ khách hàng | E16: Tất cả các trường nhập hợp lệ | F16: Ứng dụng đang chạy; dữ liệu mẫu đã nạp | G16: 1. Chọn "Thêm khách hàng" → Form hiển thị 2. Nhập Họ tên 3. Nhập Email 4. Nhập SĐT 5. Nhập Địa chỉ 6. Nhấn "Lưu khách hàng" → Hiển thị thông báo thành công | H16: Khách Kiểm Thử 106379 kt106379@test.vn 0910637911 Hà Đông, Hà Nội | I16: Hiển thị "Thêm khách hàng thành công", khách hàng xuất hiện trong danh sách | J16: Thông báo thành công, khách hàng có trong danh sách | K16: Pass | N16: Nhóm kiểm thử | O16: 03/10/2026
A17: 13 | B17: UC1.1-TC008 | C17: LỄ TÂN | D17: UC1.1 Tạo mới hồ sơ khách hàng | E17: SĐT trùng với khách hàng đã có | F17: Ứng dụng đang chạy; dữ liệu mẫu đã nạp | G17: 1. Chọn "Thêm khách hàng" → Form hiển thị 2. Nhập Họ tên, Email mới, Địa chỉ 3. Nhập SĐT đã tồn tại (của Nguyễn Huy) 4. Nhấn "Lưu khách hàng" → Hiển thị thông báo lỗi | H17: Khách Trùng SĐT / trungsdt@test.vn / Hà Nội 0911000001 | I17: Hiển thị lỗi số điện thoại đã tồn tại, không tạo khách hàng (quy tắc nghiệp vụ UC1.1) | J17: Hệ thống vẫn lưu khách hàng có SĐT trùng 0911000001 | K17: Fail | L17: Trung bình | M17: BUG-007 | N17: Nhóm kiểm thử | O17: 03/10/2026
A18: 14 | B18: UC1.1-TC009 | C18: LỄ TÂN | D18: UC1.1 Tạo mới hồ sơ khách hàng | E18: Email trùng với khách hàng đã có | F18: Ứng dụng đang chạy; dữ liệu mẫu đã nạp | G18: 1. Chọn "Thêm khách hàng" → Form hiển thị 2. Nhập Họ tên, SĐT mới, Địa chỉ 3. Nhập Email đã tồn tại 4. Nhấn "Lưu khách hàng" → Hiển thị thông báo lỗi | H18: Khách Trùng Email / 0977000999 / Hà Nội owner.huy@example.com | I18: Hiển thị lỗi email đã tồn tại, không tạo khách hàng | J18: Hệ thống vẫn lưu khách hàng có email trùng | K18: Fail | L18: Trung bình | M18: BUG-008 | N18: Nhóm kiểm thử | O18: 03/10/2026
A19: 15 | B19: UC1.1-TC010 | C19: LỄ TÂN | D19: UC1.1 Tạo mới hồ sơ khách hàng | E19: Bỏ trống Địa chỉ (trường không bắt buộc), các trường khác hợp lệ | F19: Ứng dụng đang chạy; dữ liệu mẫu đã nạp | G19: 1. Chọn "Thêm khách hàng" → Form hiển thị 2. Nhập Họ tên, Email, SĐT hợp lệ 3. Bỏ trống Địa chỉ 4. Nhấn "Lưu khách hàng" → Hiển thị thông báo thành công | H19: Khách Không Địa Chỉ / kdc106379@test.vn / 0910637922 | I19: Hiển thị "Thêm khách hàng thành công" (Địa chỉ không có dấu * nên không bắt buộc) | J19: Hiển thị "Không thể thêm khách hàng" kèm lỗi JSON: "String must contain at least 1 character(s)", path ["address"] | K19: Fail | L19: Cao | M19: BUG-002 | N19: Nhóm kiểm thử | O19: 03/10/2026
A20: 16 | B20: UC1.3-TC001 | C20: LỄ TÂN | D20: UC1.3 Chỉnh sửa hồ sơ khách hàng | E20: Cập nhật địa chỉ khách hàng hợp lệ | F20: Ứng dụng đang chạy; dữ liệu mẫu đã nạp | G20: 1. Chọn "Chỉnh sửa" tại khách hàng vừa tạo → Form cập nhật hiển thị dữ liệu cũ 2. Sửa Địa chỉ 3. Nhấn "Lưu" → Hiển thị thông báo thành công | H20: Cầu Giấy, Hà Nội | I20: Hiển thị "Cập nhật khách hàng thành công", địa chỉ mới hiển thị trong danh sách | J20: Cập nhật thành công, địa chỉ mới hiển thị | K20: Pass | N20: Nhóm kiểm thử | O20: 03/10/2026
A21: 17 | B21: UC1.3-TC002 | C21: LỄ TÂN | D21: UC1.3 Chỉnh sửa hồ sơ khách hàng | E21: Cập nhật SĐT không hợp lệ | F21: Ứng dụng đang chạy; dữ liệu mẫu đã nạp | G21: 1. Chọn "Chỉnh sửa" tại khách hàng → Form cập nhật hiển thị 2. Sửa SĐT thành 3 chữ số 3. Nhấn "Lưu" → Hiển thị thông báo lỗi | H21: 123 | I21: Hiển thị lỗi "Số điện thoại phải gồm đúng 10 chữ số", không lưu | J21: Hiển thị lỗi SĐT, không lưu | K21: Pass | N21: Nhóm kiểm thử | O21: 03/10/2026
A22: 18 | B22: UC1.4-TC001 | C22: LỄ TÂN | D22: UC1.4 Tạm khóa / Duyệt hồ sơ khách hàng | E22: Tạm khóa khách hàng đang hoạt động | F22: Ứng dụng đang chạy; dữ liệu mẫu đã nạp | G22: 1. Truy cập Quản lý khách hàng → Danh sách hiển thị 2. Nhấn "Tạm khóa" tại khách hàng vừa tạo → Trạng thái chuyển "Chờ duyệt" | H22: Khách Kiểm Thử 106379 | I22: Hiển thị "Đã cập nhật trạng thái khách hàng", trạng thái đổi thành "Chờ duyệt" | J22: Trạng thái chuyển sang "Chờ duyệt" | K22: Pass | N22: Nhóm kiểm thử | O22: 03/10/2026
A23: 19 | B23: UC1.4-TC002 | C23: LỄ TÂN | D23: UC1.4 Tạm khóa / Duyệt hồ sơ khách hàng | E23: Duyệt lại khách hàng đang bị khóa | F23: Ứng dụng đang chạy; dữ liệu mẫu đã nạp | G23: 1. Nhấn "Duyệt" tại khách hàng đang "Chờ duyệt" → Trạng thái chuyển "Đang hoạt động" | H23: Khách Kiểm Thử 106379 | I23: Hiển thị "Đã duyệt khách hàng", trạng thái đổi thành "Đang hoạt động" | J23: Khách hàng được duyệt | K23: Pass | N23: Nhóm kiểm thử | O23: 03/10/2026
A24: 20 | B24: UC1.5-TC001 | C24: LỄ TÂN | D24: UC1.5 Tìm kiếm khách hàng / thú cưng | E24: Tìm khách hàng theo tên | F24: Ứng dụng đang chạy; dữ liệu mẫu đã nạp | G24: 1. Nhập tên vào ô tìm kiếm → Danh sách được lọc | H24: Trần Lan | I24: Chỉ hiển thị khách hàng "Trần Lan" | J24: Ô tìm kiếm mất focus sau ký tự đầu – chỉ nhận "T", danh sách lọc sai | K24: Fail | L24: Cao | M24: BUG-003 | N24: Nhóm kiểm thử | O24: 03/10/2026
A25: 21 | B25: UC1.5-TC002 | C25: LỄ TÂN | D25: UC1.5 Tìm kiếm khách hàng / thú cưng | E25: Tìm khách hàng theo số điện thoại | F25: Ứng dụng đang chạy; dữ liệu mẫu đã nạp | G25: 1. Nhập SĐT vào ô tìm kiếm → Danh sách được lọc | H25: 0911000003 | I25: Hiển thị khách hàng "Phạm Tuấn" | J25: Ô tìm kiếm mất focus sau ký tự đầu – chỉ nhận "0", danh sách lọc sai | K25: Fail | L25: Cao | M25: BUG-004 | N25: Nhóm kiểm thử | O25: 03/10/2026
A26: 22 | B26: UC1.5-TC003 | C26: LỄ TÂN | D26: UC1.5 Tìm kiếm khách hàng / thú cưng | E26: Tìm với từ khóa không tồn tại | F26: Ứng dụng đang chạy; dữ liệu mẫu đã nạp | G26: 1. Nhập từ khóa không có trong dữ liệu → Danh sách rỗng | H26: zzzkhongco | I26: Hiển thị "Không có khách hàng phù hợp." | J26: Hiển thị "Không có khách hàng phù hợp." (ô tìm kiếm chỉ nhận "z") | K26: Pass | N26: Nhóm kiểm thử | O26: 03/10/2026
A27: 23 | B27: UC1.5-TC004 | C27: LỄ TÂN | D27: UC1.5 Tìm kiếm khách hàng / thú cưng | E27: Tìm thú cưng theo tên chủ nuôi | F27: Ứng dụng đang chạy; dữ liệu mẫu đã nạp | G27: 1. Nhập tên khách hàng vào ô "Tìm thú cưng theo tên khách hàng" → Hiển thị thú cưng của khách | H27: Phạm Tuấn | I27: Hiển thị đúng 2 thú cưng của khách hàng Phạm Tuấn (Bun, Nau) | J27: Hiển thị Nau, Bun | K27: Pass | N27: Nhóm kiểm thử | O27: 03/10/2026
A28: 24 | B28: UC1.5-TC005 | C28: LỄ TÂN | D28: UC1.5 Tìm kiếm khách hàng / thú cưng | E28: Lọc khách hàng theo trạng thái "Chờ duyệt" | F28: Ứng dụng đang chạy; dữ liệu mẫu đã nạp | G28: 1. Truy cập Quản lý khách hàng → Danh sách 30 khách hàng mẫu hiển thị 2. Chọn bộ lọc trạng thái "Chờ duyệt" → Danh sách được lọc | H28: Chờ duyệt | I28: Hiển thị đúng 3 khách hàng chờ duyệt: Huỳnh Hoàng Nam, Ngô Mỹ Duyên, Huỳnh Bích Ngọc | J28: Hiển thị đúng 3 khách hàng chờ duyệt | K28: Pass | N28: Nhóm kiểm thử | O28: 03/10/2026
A29: 25 | B29: UC1.5-TC006 | C29: LỄ TÂN | D29: UC1.5 Tìm kiếm khách hàng / thú cưng | E29: Lọc khách hàng theo trạng thái "Đang hoạt động" | F29: Ứng dụng đang chạy; dữ liệu mẫu đã nạp | G29: 1. Truy cập Quản lý khách hàng → Danh sách hiển thị 2. Chọn bộ lọc trạng thái "Đang hoạt động" → Danh sách được lọc | H29: Đang hoạt động | I29: Hiển thị toàn bộ khách hàng đang hoạt động (tổng số khách hàng trừ 3 khách chờ duyệt), không có khách chờ duyệt | J29: Hiển thị 30 khách hàng đang hoạt động | K29: Pass | N29: Nhóm kiểm thử | O29: 03/10/2026
A30: 26 | B30: UC1.2-TC001 | C30: LỄ TÂN | D30: UC1.2 Tạo mới hồ sơ thú cưng | E30: Bỏ trống Tên và Loài thú cưng | F30: Ứng dụng đang chạy; dữ liệu mẫu đã nạp | G30: 1. Nhấn "Thêm thú cưng" tại khách hàng Nguyễn Huy → Form thêm thú cưng hiển thị 2. Bỏ trống Tên, Loài 3. Nhấn "Lưu thú cưng" → Hiển thị thông báo lỗi | I30: Hiển thị lỗi "Tên thú cưng là bắt buộc", "Loài là bắt buộc" | J30: Hiển thị 2 thông báo lỗi | K30: Pass | N30: Nhóm kiểm thử | O30: 03/10/2026
A31: 27 | B31: UC1.2-TC002 | C31: LỄ TÂN | D31: UC1.2 Tạo mới hồ sơ thú cưng | E31: Nhập Tên, bỏ trống Loài | F31: Ứng dụng đang chạy; dữ liệu mẫu đã nạp | G31: 1. Nhấn "Thêm thú cưng" → Form hiển thị 2. Nhập Tên thú cưng 3. Bỏ trống Loài, nhấn "Lưu thú cưng" → Hiển thị thông báo lỗi | H31: Mướp | I31: Hiển thị lỗi "Loài là bắt buộc" | J31: Hiển thị lỗi Loài | K31: Pass | N31: Nhóm kiểm thử | O31: 03/10/2026
A32: 28 | B32: UC1.2-TC003 | C32: LỄ TÂN | D32: UC1.2 Tạo mới hồ sơ thú cưng | E32: Thông tin thú cưng hợp lệ | F32: Ứng dụng đang chạy; dữ liệu mẫu đã nạp | G32: 1. Nhấn "Thêm thú cưng" tại Nguyễn Huy → Form hiển thị, khách hàng tự điền 2. Nhập Tên 3. Chọn Loài 4. Nhập Tuổi, Cân nặng, Microchip 5. Nhấn "Lưu thú cưng" → Hiển thị thông báo thành công | H32: Bông 106379 Mèo 2 / 3.5 / MC-106379 | I32: Hiển thị "Thêm thú cưng thành công", số thú cưng của khách hàng tăng 1 | J32: Thêm thú cưng thành công | K32: Pass | N32: Nhóm kiểm thử | O32: 03/10/2026
A33: 29 | B33: UC1.2-TC004 | C33: LỄ TÂN | D33: UC1.2 Tạo mới hồ sơ thú cưng | E33: Mã microchip trùng với thú cưng đã có | F33: Ứng dụng đang chạy; dữ liệu mẫu đã nạp | G33: 1. Nhấn "Thêm thú cưng" → Form hiển thị 2. Nhập Tên, chọn Loài 3. Nhập microchip đã dùng ở TC003 4. Nhấn "Lưu thú cưng" → Hiển thị thông báo lỗi | H33: Mực / Chó MC-106379 | I33: Hiển thị "Microchip đã tồn tại, vui lòng kiểm tra lại." (luồng thay thế UC1.2) | J33: Hệ thống vẫn lưu thú cưng có microchip trùng | K33: Fail | L33: Trung bình | M33: BUG-009 | N33: Nhóm kiểm thử | O33: 03/10/2026
A34: 30 | B34: UC1.2-TC005 | C34: LỄ TÂN | D34: UC1.2 Tạo mới hồ sơ thú cưng | E34: Kiểm thử giá trị biên: Tuổi âm | F34: Ứng dụng đang chạy; dữ liệu mẫu đã nạp | G34: 1. Nhấn "Thêm thú cưng" → Form hiển thị 2. Nhập Tên, chọn Loài 3. Nhập Tuổi âm 4. Nhấn "Lưu thú cưng" → Hiển thị thông báo lỗi | H34: Na / Thỏ -1 | I34: Không lưu thú cưng, hiển thị thông báo lỗi | J34: Hiển thị "Không thể thêm thú cưng" | K34: Pass | N34: Nhóm kiểm thử | O34: 03/10/2026
A35: 31 | B35: UC2.1-TC001 | C35: LỄ TÂN | D35: UC2.1 Đặt lịch khám | E35: Bỏ trống tất cả các trường và nhấn "Lưu" | F35: Ứng dụng đang chạy; dữ liệu mẫu đã nạp | G35: 1. Chọn "Tạo lịch hẹn" → Form tạo lịch hẹn hiển thị 2. Không chọn khách hàng, thú cưng, ngày, dịch vụ 3. Nhấn nút lưu → Hiển thị thông báo lỗi | I35: Hiển thị thông báo "Vui lòng chọn khách hàng", "Vui lòng chọn thú cưng"... | J35: Form không gửi nhưng không hiển thị thông báo lỗi nào cho người dùng | K35: Fail | L35: Thấp | M35: BUG-020 | N35: Nhóm kiểm thử | O35: 03/10/2026
A36: 32 | B36: UC2.1-TC002 | C36: LỄ TÂN | D36: UC2.1 Đặt lịch khám | E36: Đặt lịch hợp lệ | F36: Ứng dụng đang chạy; dữ liệu mẫu đã nạp | G36: 1. Chọn "Tạo lịch hẹn" → Form hiển thị 2. Chọn Khách hàng, Thú cưng 3. Chọn Bác sĩ 4. Chọn Ngày, Giờ khám 5. Chọn Dịch vụ 6. Nhấn nút lưu → Hiển thị thông báo thành công | H36: Nguyễn Huy / Bông 106379 Bác sĩ đầu tiên trong danh sách 2026-10-04 15:00 Khám tổng quát | I36: Hiển thị "Đặt lịch thành công" | J36: Đặt lịch thành công | K36: Pass | N36: Nhóm kiểm thử | O36: 03/10/2026
A37: 33 | B37: UC2.1-TC003 | C37: LỄ TÂN | D37: UC2.1 Đặt lịch khám | E37: Đặt lịch trùng khung giờ của bác sĩ | F37: Ứng dụng đang chạy; dữ liệu mẫu đã nạp | G37: 1. Chọn "Tạo lịch hẹn" → Form hiển thị 2. Chọn khách hàng, thú cưng khác 3. Chọn cùng Bác sĩ, Ngày, Giờ với TC002 4. Chọn dịch vụ, nhấn lưu → Hiển thị thông báo lỗi | H37: Trần Lan 2026-10-04 15:00 Tiêm phòng | I37: Hiển thị "Không thể đặt lịch" – bác sĩ đã có lịch trong khung giờ | J37: Hiển thị "Không thể đặt lịch" (Veterinarian already has an appointment in this timeslot) | K37: Pass | N37: Nhóm kiểm thử | O37: 03/10/2026
A38: 34 | B38: UC2.1-TC004 | C38: LỄ TÂN | D38: UC2.1 Đặt lịch khám | E38: Đặt lịch trùng khung giờ của thú cưng | F38: Ứng dụng đang chạy; dữ liệu mẫu đã nạp | G38: 1. Chọn "Tạo lịch hẹn" → Form hiển thị 2. Chọn cùng khách hàng, thú cưng với TC002, không chọn bác sĩ 3. Chọn cùng Ngày, Giờ 4. Chọn dịch vụ, nhấn lưu → Hiển thị thông báo lỗi | H38: Bông 106379 2026-10-04 15:00 Tái khám | I38: Hiển thị "Không thể đặt lịch" – thú cưng đã có lịch trong khung giờ | J38: Hiển thị "Không thể đặt lịch" (Pet already has an appointment in this timeslot) | K38: Pass | N38: Nhóm kiểm thử | O38: 03/10/2026
A39: 35 | B39: UC2.1-TC005 | C39: LỄ TÂN | D39: UC2.1 Đặt lịch khám | E39: Đặt lịch vào ngày trong quá khứ | F39: Ứng dụng đang chạy; dữ liệu mẫu đã nạp | G39: 1. Chọn "Tạo lịch hẹn" → Form hiển thị 2. Chọn khách hàng, thú cưng, dịch vụ hợp lệ 3. Chọn ngày hôm qua 4. Nhấn lưu → Hiển thị thông báo lỗi | H39: Nguyễn Huy / Bông 106379 2026-10-02 10:00 | I39: Hệ thống từ chối lịch hẹn trong quá khứ | J39: Hệ thống vẫn tạo lịch hẹn ngày 2026-10-02 | K39: Fail | L39: Trung bình | M39: BUG-010 | N39: Nhóm kiểm thử | O39: 03/10/2026
A40: 36 | B40: UC2.2-TC001 | C40: LỄ TÂN | D40: UC2.2 Xác nhận / Hủy / Hoàn thành lịch hẹn | E40: Xác nhận lịch hẹn đang chờ | F40: Ứng dụng đang chạy; dữ liệu mẫu đã nạp | G40: 1. Có lịch hẹn "Chờ xác nhận" ngày mai → Lịch hẹn hiển thị ở tab "Quản lý toàn bộ" 2. Nhấn "Xác nhận" tại lịch hẹn → Trạng thái "Đã xác nhận" | H40: Cún Xác Nhận / 2026-10-04 11:00 | I40: Hiển thị "Đã cập nhật lịch hẹn", lịch hẹn chuyển trạng thái "Đã xác nhận" | J40: Lịch hẹn chuyển "Đã xác nhận" (confirmed) | K40: Pass | N40: Nhóm kiểm thử | O40: 03/10/2026
A41: 37 | B41: UC2.2-TC002 | C41: LỄ TÂN | D41: UC2.2 Xác nhận / Hủy / Hoàn thành lịch hẹn | E41: Hoàn thành lịch hẹn đã xác nhận | F41: Ứng dụng đang chạy; dữ liệu mẫu đã nạp | G41: 1. Nhấn "Hoàn thành" tại lịch hẹn đã xác nhận ở TC001 → Trạng thái "Hoàn thành" | H41: Cún Xác Nhận | I41: Hiển thị "Đã cập nhật lịch hẹn", nút "Hủy lịch" bị vô hiệu | J41: Lịch hẹn hoàn thành, nút Hủy lịch bị khóa | K41: Pass | N41: Nhóm kiểm thử | O41: 03/10/2026
A42: 38 | B42: UC2.2-TC003 | C42: LỄ TÂN | D42: UC2.2 Xác nhận / Hủy / Hoàn thành lịch hẹn | E42: Hủy lịch hẹn còn trên 1 tiếng | F42: Ứng dụng đang chạy; dữ liệu mẫu đã nạp | G42: 1. Tạo lịch hẹn ngày mai cho thú cưng mới → Lịch hẹn "Chờ xác nhận" 2. Nhấn "Hủy lịch" → Trạng thái "Đã hủy" | H42: 2026-10-04 09:00 | I42: Hiển thị "Đã hủy lịch hẹn" | J42: Lịch hẹn đã hủy | K42: Pass | N42: Nhóm kiểm thử | O42: 03/10/2026
A43: 39 | B43: UC2.2-TC004 | C43: LỄ TÂN | D43: UC2.2 Xác nhận / Hủy / Hoàn thành lịch hẹn | E43: Hủy lịch hẹn khi còn dưới 1 tiếng | F43: Ứng dụng đang chạy; dữ liệu mẫu đã nạp | G43: 1. Có lịch hẹn bắt đầu sau 30 phút → Lịch hẹn "Chờ xác nhận" 2. Nhấn "Hủy lịch" → Hiển thị thông báo lỗi | H43: Giờ hiện tại + 30 phút | I43: Hệ thống từ chối – chỉ được hủy trước giờ hẹn ít nhất 1 tiếng (R2.2) | J43: Lịch hẹn vẫn bị hủy dù chỉ còn 30 phút | K43: Fail | L43: Trung bình | M43: BUG-011 | N43: Nhóm kiểm thử | O43: 03/10/2026
A44: 40 | B44: UC3.1-TC001 | C44: BÁC SĨ | D44: UC3.1 Tạo hồ sơ khám bệnh | E44: Bỏ trống tất cả các trường và nhấn "Lưu hồ sơ" | F44: Ứng dụng đang chạy; dữ liệu mẫu đã nạp | G44: 1. Mở tab "Tạo hồ sơ mới" → Form hồ sơ khám hiển thị 2. Không nhập dữ liệu, nhấn "Lưu hồ sơ" → Hiển thị thông báo lỗi | I44: Hiển thị lỗi "Vui lòng chọn thú cưng", "Vui lòng chọn bác sĩ", "Triệu chứng là bắt buộc", "Chẩn đoán là bắt buộc", "Phác đồ điều trị là bắt buộc" | J44: Hiển thị đủ 5 thông báo lỗi | K44: Pass | N44: Nhóm kiểm thử | O44: 03/10/2026
A45: 41 | B45: UC3.1-TC002 | C45: BÁC SĨ | D45: UC3.1 Tạo hồ sơ khám bệnh | E45: Bỏ trống Chẩn đoán | F45: Ứng dụng đang chạy; dữ liệu mẫu đã nạp | G45: 1. Mở tab "Tạo hồ sơ mới" → Form hiển thị 2. Chọn Thú cưng, Bác sĩ 3. Nhập Triệu chứng, Điều trị; bỏ trống Chẩn đoán 4. Nhấn "Lưu hồ sơ" → Hiển thị thông báo lỗi | H45: Bông 106379 Bỏ ăn 2 ngày / Truyền dịch | I45: Hiển thị lỗi "Chẩn đoán là bắt buộc" | J45: Hiển thị lỗi chẩn đoán | K45: Pass | N45: Nhóm kiểm thử | O45: 03/10/2026
A46: 42 | B46: UC3.1-TC003 | C46: BÁC SĨ | D46: UC3.1 Tạo hồ sơ khám bệnh | E46: Nhập đầy đủ thông tin hồ sơ khám hợp lệ | F46: Ứng dụng đang chạy; dữ liệu mẫu đã nạp | G46: 1. Mở tab "Tạo hồ sơ mới" → Form hiển thị 2. Chọn Thú cưng, Bác sĩ 3. Nhập Triệu chứng 4. Nhập Chẩn đoán 5. Nhập Phác đồ điều trị 6. Nhấn "Lưu hồ sơ" → Hiển thị thông báo thành công | H46: Bông 106379 Bỏ ăn 2 ngày, nôn Viêm dạ dày 106379 Truyền dịch, kháng sinh 5 ngày | I46: Hiển thị "Lưu hồ sơ khám thành công", hồ sơ xuất hiện trong danh sách | J46: Lưu hồ sơ khám thành công | K46: Pass | N46: Nhóm kiểm thử | O46: 03/10/2026
A47: 43 | B47: UC3.3-TC001 | C47: BÁC SĨ | D47: UC3.3 Tra cứu lịch sử khám | E47: Tìm hồ sơ theo chẩn đoán | F47: Ứng dụng đang chạy; dữ liệu mẫu đã nạp | G47: 1. Mở tab "Danh sách hồ sơ" → Danh sách hồ sơ hiển thị 2. Nhập chẩn đoán vào ô tìm kiếm → Danh sách được lọc | H47: Viêm dạ dày 106379 | I47: Hiển thị "1 hồ sơ" có chẩn đoán tương ứng | J47: Hiển thị 1 hồ sơ đúng chẩn đoán | K47: Pass | N47: Nhóm kiểm thử | O47: 03/10/2026
A48: 44 | B48: UC3.3-TC002 | C48: BÁC SĨ | D48: UC3.3 Tra cứu lịch sử khám | E48: Tìm hồ sơ với từ khóa không tồn tại | F48: Ứng dụng đang chạy; dữ liệu mẫu đã nạp | G48: 1. Nhập từ khóa không có trong dữ liệu → Danh sách rỗng | H48: zzzkhongco | I48: Hiển thị "Không tìm thấy hồ sơ theo điều kiện tìm kiếm." | J48: Hiển thị thông báo không tìm thấy | K48: Pass | N48: Nhóm kiểm thử | O48: 03/10/2026
A49: 45 | B49: UC3.3-TC003 | C49: BÁC SĨ | D49: UC3.3 Tra cứu lịch sử khám | E49: Tìm hồ sơ theo chẩn đoán có nhiều kết quả | F49: Ứng dụng đang chạy; dữ liệu mẫu đã nạp | G49: 1. Mở tab "Danh sách hồ sơ" → Danh sách hồ sơ mẫu hiển thị 2. Nhập chẩn đoán vào ô tìm kiếm → Danh sách được lọc | H49: Viêm da dị ứng | I49: Hiển thị "4 hồ sơ", tất cả có chẩn đoán "Viêm da dị ứng" | J49: Hiển thị 4 hồ sơ "Viêm da dị ứng" | K49: Pass | N49: Nhóm kiểm thử | O49: 03/10/2026
A50: 46 | B50: UC3.3-TC004 | C50: BÁC SĨ | D50: UC3.3 Tra cứu lịch sử khám | E50: Hiển thị toàn bộ lịch sử khám | F50: Ứng dụng đang chạy; dữ liệu mẫu đã nạp | G50: 1. Mở tab "Danh sách hồ sơ", không nhập từ khóa → Danh sách đầy đủ | I50: Số hồ sơ hiển thị bằng tổng số hồ sơ trong CSDL (43 hồ sơ mẫu + hồ sơ tạo ở UC3.1-TC003) | J50: Hiển thị đủ 44 hồ sơ | K50: Pass | N50: Nhóm kiểm thử | O50: 03/10/2026
A51: 47 | B51: UC2.4-TC001 | C51: BÁC SĨ | D51: UC2.4 Quản lý ca làm việc bác sĩ | E51: Không chọn bác sĩ và ngày trực | F51: Ứng dụng đang chạy; dữ liệu mẫu đã nạp | G51: 1. Chọn "Tạo ca trực" → Form tạo ca trực hiển thị 2. Không chọn bác sĩ, ngày; nhấn "Lưu ca trực" → Hiển thị thông báo lỗi | I51: Hiển thị "Vui lòng chọn bác sĩ và ngày trực" | J51: Hiển thị thông báo lỗi | K51: Pass | N51: Nhóm kiểm thử | O51: 03/10/2026
A52: 48 | B52: UC2.4-TC002 | C52: BÁC SĨ | D52: UC2.4 Quản lý ca làm việc bác sĩ | E52: Tạo ca trực hợp lệ | F52: Ứng dụng đang chạy; dữ liệu mẫu đã nạp | G52: 1. Chọn "Tạo ca trực" → Form hiển thị 2. Chọn Bác sĩ, Ngày trực 3. Nhập giờ bắt đầu – kết thúc 4. Nhấn "Lưu ca trực" → Hiển thị thông báo thành công | H52: Bác sĩ đầu tiên / 2026-10-06 08:00 – 12:00 | I52: Hiển thị "Đã tạo ca trực" | J52: Tạo ca trực thành công | K52: Pass | N52: Nhóm kiểm thử | O52: 03/10/2026
A53: 49 | B53: UC2.4-TC003 | C53: BÁC SĨ | D53: UC2.4 Quản lý ca làm việc bác sĩ | E53: Giờ kết thúc sớm hơn giờ bắt đầu | F53: Ứng dụng đang chạy; dữ liệu mẫu đã nạp | G53: 1. Chọn "Tạo ca trực" → Form hiển thị 2. Chọn Bác sĩ, Ngày trực 3. Nhập giờ bắt đầu 17:00, kết thúc 13:00 4. Nhấn "Lưu ca trực" → Hiển thị thông báo lỗi | H53: 2026-10-06 17:00 – 13:00 | I53: Hệ thống từ chối ca trực có giờ kết thúc trước giờ bắt đầu | J53: Ca trực 17:00 – 13:00 vẫn được tạo | K53: Fail | L53: Trung bình | M53: BUG-012 | N53: Nhóm kiểm thử | O53: 03/10/2026
A54: 50 | B54: UC2.4-TC004 | C54: BÁC SĨ | D54: UC2.4 Quản lý ca làm việc bác sĩ | E54: Tạo ca trực trùng với ca đã có của bác sĩ | F54: Ứng dụng đang chạy; dữ liệu mẫu đã nạp | G54: 1. Chọn "Tạo ca trực" → Form hiển thị 2. Chọn cùng Bác sĩ, Ngày với TC002 3. Nhập giờ 09:00 – 11:00 (giao với 08:00 – 12:00) 4. Nhấn "Lưu ca trực" → Hiển thị thông báo lỗi | H54: 2026-10-06 09:00 – 11:00 | I54: Hệ thống báo trùng ca, không tạo ca trực (R2.4 – tránh trùng lịch) | J54: Ca trực trùng giờ vẫn được tạo | K54: Fail | L54: Trung bình | M54: BUG-013 | N54: Nhóm kiểm thử | O54: 03/10/2026
A55: 51 | B55: UC2.4-TC005 | C55: BÁC SĨ | D55: UC2.4 Quản lý ca làm việc bác sĩ | E55: Xóa ca trực | F55: Ứng dụng đang chạy; dữ liệu mẫu đã nạp | G55: 1. Nhấn "Xóa ca" tại một ca trực → Ca trực bị xóa khỏi danh sách | I55: Hiển thị "Đã xóa ca trực" | J55: Xóa ca trực thành công | K55: Pass | N55: Nhóm kiểm thử | O55: 03/10/2026
A56: 52 | B56: UC8.2-TC001 | C56: BÁC SĨ | D56: UC8.2 Theo dõi thú cưng qua camera | E56: Xem danh sách camera đang trực tuyến | F56: Ứng dụng đang chạy; dữ liệu mẫu đã nạp | G56: 1. Chọn menu "Camera giám sát" → Danh sách camera hiển thị | I56: Hiển thị 12 camera trực tuyến (Phòng 01–03, 05–08, 10–12, 14, 15); không hiển thị 3 camera tắt (04, 09, 13) | J56: Hiển thị đủ 12 camera trực tuyến | K56: Pass | N56: Nhóm kiểm thử | O56: 03/10/2026
A57: 53 | B57: UC8.2-TC002 | C57: BÁC SĨ | D57: UC8.2 Theo dõi thú cưng qua camera | E57: Lọc camera theo trạng thái "Ngoại tuyến" | F57: Ứng dụng đang chạy; dữ liệu mẫu đã nạp | G57: 1. Chọn menu "Camera giám sát" → Danh sách camera hiển thị 2. Chọn bộ lọc trạng thái "Ngoại tuyến" → Hiển thị camera ngoại tuyến | H57: Phòng 04, 09, 13 (camera đang tắt) | I57: Hiển thị 3 camera Phòng 04, 09, 13 với nhãn "Ngoại tuyến" | J57: Danh sách trống – API /api/camera-streams chỉ trả về camera đang hoạt động nên bộ lọc "Ngoại tuyến" không bao giờ có kết quả | K57: Fail | L57: Thấp | M57: BUG-021 | N57: Nhóm kiểm thử | O57: 03/10/2026
A58: 54 | B58: UC8.2-TC003 | C58: BÁC SĨ | D58: UC8.2 Theo dõi thú cưng qua camera | E58: Tìm camera theo số phòng | F58: Ứng dụng đang chạy; dữ liệu mẫu đã nạp | G58: 1. Chọn menu "Camera giám sát" → Danh sách camera hiển thị 2. Nhập số phòng vào ô tìm kiếm → Danh sách được lọc | H58: Phòng 12 | I58: Chỉ hiển thị camera Phòng 12 | J58: Chỉ hiển thị camera Phòng 12 | K58: Pass | N58: Nhóm kiểm thử | O58: 03/10/2026
A59: 55 | B59: UC6.1-TC001 | C59: QUẢN TRỊ VIÊN / KẾ TOÁN | D59: UC6.1 Quản lý thông tin bác sĩ | E59: Bỏ trống tất cả các trường và nhấn "Tạo bác sĩ" | F59: Ứng dụng đang chạy; dữ liệu mẫu đã nạp | G59: 1. Chọn "Thêm bác sĩ" → Form thêm bác sĩ hiển thị 2. Không nhập dữ liệu, nhấn "Tạo bác sĩ" → Hiển thị thông báo lỗi | I59: Hiển thị thông báo lỗi rõ ràng cho từng trường bắt buộc | J59: Hiển thị "Không thể thêm bác sĩ" kèm chuỗi lỗi kỹ thuật (JSON của Zod), khó hiểu với người dùng | K59: Fail | L59: Thấp | M59: BUG-022 | N59: Nhóm kiểm thử | O59: 03/10/2026
A60: 56 | B60: UC6.1-TC002 | C60: QUẢN TRỊ VIÊN / KẾ TOÁN | D60: UC6.1 Quản lý thông tin bác sĩ | E60: Email bác sĩ sai định dạng | F60: Ứng dụng đang chạy; dữ liệu mẫu đã nạp | G60: 1. Chọn "Thêm bác sĩ" → Form hiển thị 2. Nhập Họ tên, Chuyên khoa, Mã hành nghề hợp lệ 3. Nhập Email sai 4. Nhấn "Tạo bác sĩ" → Hiển thị thông báo lỗi | H60: BS. Hà An / Nội khoa / VET-106379 haan.vet | I60: Hiển thị "Không thể thêm bác sĩ", không tạo bác sĩ | J60: Hiển thị "Không thể thêm bác sĩ" | K60: Pass | N60: Nhóm kiểm thử | O60: 03/10/2026
A61: 57 | B61: UC6.1-TC003 | C61: QUẢN TRỊ VIÊN / KẾ TOÁN | D61: UC6.1 Quản lý thông tin bác sĩ | E61: Thêm bác sĩ hợp lệ | F61: Ứng dụng đang chạy; dữ liệu mẫu đã nạp | G61: 1. Chọn "Thêm bác sĩ" → Form hiển thị 2. Nhập Họ tên, Email 3. Nhập SĐT, Chuyên khoa, Mã hành nghề 4. Nhấn "Tạo bác sĩ" → Hiển thị thông báo thành công | H61: BS. Kiểm Thử 106379 / bs106379@petclinic.vn 0901234567 / Da liễu / VET-106379 | I61: Hiển thị "Đã thêm bác sĩ mới", bác sĩ xuất hiện trong danh sách | J61: Đã thêm bác sĩ mới | K61: Pass | N61: Nhóm kiểm thử | O61: 03/10/2026
A62: 58 | B62: UC6.1-TC004 | C62: QUẢN TRỊ VIÊN / KẾ TOÁN | D62: UC6.1 Quản lý thông tin bác sĩ | E62: Cập nhật chuyên khoa của bác sĩ | F62: Ứng dụng đang chạy; dữ liệu mẫu đã nạp | G62: 1. Nhấn "Chỉnh sửa" tại bác sĩ vừa tạo → Form cập nhật hiển thị 2. Sửa Chuyên khoa 3. Nhấn "Lưu cập nhật" → Hiển thị thông báo thành công | H62: BS. Kiểm Thử 106379 Ngoại khoa | I62: Hiển thị "Đã cập nhật bác sĩ" | J62: Cập nhật thành công | K62: Pass | N62: Nhóm kiểm thử | O62: 03/10/2026
A63: 59 | B63: UC6.1-TC005 | C63: QUẢN TRỊ VIÊN / KẾ TOÁN | D63: UC6.1 Quản lý thông tin bác sĩ | E63: Đổi trạng thái nhận lịch của bác sĩ | F63: Ứng dụng đang chạy; dữ liệu mẫu đã nạp | G63: 1. Nhấn "Đặt bận" tại bác sĩ vừa tạo → Trạng thái nhận lịch thay đổi | H63: BS. Kiểm Thử 106379 | I63: Hiển thị "Đã cập nhật trạng thái nhận lịch", nút đổi thành "Đặt sẵn sàng" | J63: Trạng thái đổi thành bận | K63: Pass | N63: Nhóm kiểm thử | O63: 03/10/2026
A64: 60 | B64: UC6.1-TC006 | C64: QUẢN TRỊ VIÊN / KẾ TOÁN | D64: UC6.1 Quản lý thông tin bác sĩ | E64: Tìm bác sĩ theo chuyên khoa | F64: Ứng dụng đang chạy; dữ liệu mẫu đã nạp | G64: 1. Nhập chuyên khoa vào ô tìm kiếm → Danh sách được lọc | H64: Ngoại khoa | I64: Danh sách chỉ gồm bác sĩ có chuyên khoa "Ngoại khoa" | J64: Hiển thị BS. Kiểm Thử 085746 | K64: Pass | N64: Nhóm kiểm thử | O64: 03/10/2026
A65: 61 | B65: UC4.1-TC001 | C65: QUẢN TRỊ VIÊN / KẾ TOÁN | D65: UC4.1 Nhập kho thuốc / vật tư | E65: Bỏ trống các trường bắt buộc | F65: Ứng dụng đang chạy; dữ liệu mẫu đã nạp | G65: 1. Chọn "Thêm vật tư" → Form thêm vật tư hiển thị 2. Không nhập dữ liệu, nhấn "Lưu vật tư" → Hiển thị thông báo lỗi | I65: Hiển thị lỗi "Mã vật tư là bắt buộc", "Tên vật tư là bắt buộc", "Danh mục là bắt buộc", "Đơn vị là bắt buộc", "Giá là bắt buộc" | J65: Form không lưu, nhưng thiếu thông báo: "Giá là bắt buộc" | K65: Fail | L65: Thấp | M65: BUG-023 | N65: Nhóm kiểm thử | O65: 03/10/2026
A66: 62 | B66: UC4.1-TC002 | C66: QUẢN TRỊ VIÊN / KẾ TOÁN | D66: UC4.1 Nhập kho thuốc / vật tư | E66: Kiểm thử giá trị biên: Tồn kho âm | F66: Ứng dụng đang chạy; dữ liệu mẫu đã nạp | G66: 1. Chọn "Thêm vật tư" → Form hiển thị 2. Nhập thông tin hợp lệ 3. Nhập Tồn kho âm 4. Nhấn "Lưu vật tư" → Hiển thị thông báo lỗi | H66: TEST-NEG / Thuốc thử / Thuốc / Hộp / 50000 -5 | I66: Hiển thị lỗi "Tồn kho không hợp lệ" | J66: Trình duyệt chặn: "Giá trị phải lớn hơn hoặc bằng 0." | K66: Pass | N66: Nhóm kiểm thử | O66: 03/10/2026
A67: 63 | B67: UC4.1-TC003 | C67: QUẢN TRỊ VIÊN / KẾ TOÁN | D67: UC4.1 Nhập kho thuốc / vật tư | E67: Thêm vật tư hợp lệ kèm hạn sử dụng | F67: Ứng dụng đang chạy; dữ liệu mẫu đã nạp | G67: 1. Chọn "Thêm vật tư" → Form hiển thị 2. Nhập Mã, Tên 3. Chọn Danh mục, nhập Đơn vị 4. Nhập Tồn kho, Tồn tối thiểu, Giá 5. Nhập Hạn sử dụng 6. Nhấn "Lưu vật tư" → Hiển thị thông báo thành công | H67: MED-106379 / Amoxicillin KT 106379 Thuốc / Hộp 20 / 5 / 45000 2027-04-01 | I67: Hiển thị "Thêm vật tư thành công", lô hàng được tạo kèm hạn dùng | J67: Thêm vật tư thành công, 1 lô hàng được tạo | K67: Pass | N67: Nhóm kiểm thử | O67: 03/10/2026
A68: 64 | B68: UC4.1-TC004 | C68: QUẢN TRỊ VIÊN / KẾ TOÁN | D68: UC4.1 Nhập kho thuốc / vật tư | E68: Mã vật tư trùng với vật tư đã có | F68: Ứng dụng đang chạy; dữ liệu mẫu đã nạp | G68: 1. Chọn "Thêm vật tư" → Form hiển thị 2. Nhập Mã vật tư đã dùng ở TC003 3. Nhập các trường còn lại hợp lệ, nhấn "Lưu vật tư" → Hiển thị thông báo lỗi | H68: MED-106379 Thuốc trùng mã / Thuốc / Hộp / 10 / 1000 | I68: Hệ thống báo mã vật tư đã tồn tại, không tạo vật tư mới | J68: Vẫn tạo vật tư thứ hai có mã MED-085746 | K68: Fail | L68: Trung bình | M68: BUG-014 | N68: Nhóm kiểm thử | O68: 03/10/2026
A69: 65 | B69: UC4.3-TC001 | C69: QUẢN TRỊ VIÊN / KẾ TOÁN | D69: UC4.3 Cảnh báo tồn kho thấp | E69: Vật tư có tồn kho dưới mức tối thiểu | F69: Ứng dụng đang chạy; dữ liệu mẫu đã nạp | G69: 1. Thêm vật tư có Tồn kho 3, Tồn tối thiểu 10 → Vật tư được lưu 2. Quan sát trang Kho thuốc → Hiển thị cảnh báo | H69: LOW-106379 | I69: Số mặt hàng trong khung "Cảnh báo tồn kho thấp" tăng thêm 1 so với trước khi thêm | J69: Cảnh báo tăng từ 5 lên 6 mặt hàng | K69: Pass | N69: Nhóm kiểm thử | O69: 03/10/2026
A70: 66 | B70: UC4.3-TC002 | C70: QUẢN TRỊ VIÊN / KẾ TOÁN | D70: UC4.3 Cảnh báo tồn kho thấp | E70: Xem danh sách mặt hàng sắp hết | F70: Ứng dụng đang chạy; dữ liệu mẫu đã nạp | G70: 1. Truy cập Kho thuốc → Khung cảnh báo tồn kho thấp hiển thị 2. Nhấn "Xem mặt hàng sắp hết" → Danh sách chỉ còn mặt hàng sắp hết | I70: Danh sách gồm 4 mặt hàng mẫu sắp hết (Doxycycline, Thuốc nhỏ mắt, Vaccine mèo 4 bệnh, Ống truyền dịch) và vật tư thêm ở TC001; không có mặt hàng đủ tồn (Rabies Vaccine) | J70: Hiển thị đúng các mặt hàng sắp hết | K70: Pass | N70: Nhóm kiểm thử | O70: 03/10/2026
A71: 67 | B71: UC5.1-TC001 | C71: QUẢN TRỊ VIÊN / KẾ TOÁN | D71: UC5.1 Tạo hóa đơn bán thuốc | E71: Không chọn khách hàng và thuốc | F71: Ứng dụng đang chạy; dữ liệu mẫu đã nạp | G71: 1. Chọn "Tạo hóa đơn" → Form tạo hóa đơn hiển thị 2. Không chọn khách hàng, thuốc; nhấn "Tạo hóa đơn" → Hiển thị thông báo lỗi | I71: Hiển thị "Vui lòng chọn khách hàng, thuốc và số lượng hợp lệ" | J71: Hiển thị thông báo lỗi | K71: Pass | N71: Nhóm kiểm thử | O71: 03/10/2026
A72: 68 | B72: UC5.1-TC002 | C72: QUẢN TRỊ VIÊN / KẾ TOÁN | D72: UC5.1 Tạo hóa đơn bán thuốc | E72: Tạo hóa đơn hợp lệ – tồn kho tự động trừ | F72: Ứng dụng đang chạy; dữ liệu mẫu đã nạp | G72: 1. Chọn "Tạo hóa đơn" → Form hiển thị 2. Chọn Khách hàng 3. Chọn Thuốc 4. Nhập Số lượng 5. Nhấn "Tạo hóa đơn" → Hiển thị thông báo thành công | H72: Nguyễn Huy Amoxicillin KT 106379 4 | I72: Hiển thị "Tạo hóa đơn thành công", tồn kho giảm từ 20 xuống 16, tổng tiền 180.000 VND | J72: Tạo hóa đơn thành công, tồn kho còn 16, tổng 180.000 VND | K72: Pass | N72: Nhóm kiểm thử | O72: 03/10/2026
A73: 69 | B73: UC5.1-TC003 | C73: QUẢN TRỊ VIÊN / KẾ TOÁN | D73: UC5.1 Tạo hóa đơn bán thuốc | E73: Số lượng bán lớn hơn tồn kho | F73: Ứng dụng đang chạy; dữ liệu mẫu đã nạp | G73: 1. Chọn "Tạo hóa đơn" → Form hiển thị 2. Chọn Khách hàng, Thuốc 3. Nhập Số lượng lớn hơn tồn (16) 4. Nhấn "Tạo hóa đơn" → Hiển thị thông báo lỗi | H73: Trần Lan / Amoxicillin KT 106379 100 | I73: Hiển thị "Không thể tạo hóa đơn", không phát sinh hóa đơn nào | J73: Có báo lỗi nhưng vẫn phát sinh 1 hóa đơn rỗng 0 VND ở trạng thái chờ thanh toán | K73: Fail | L73: Trung bình | M73: BUG-015 | N73: Nhóm kiểm thử | O73: 03/10/2026
A74: 70 | B74: UC5.2-TC001 | C74: QUẢN TRỊ VIÊN / KẾ TOÁN | D74: UC5.2 Thanh toán hóa đơn | E74: Xác nhận đã thu tiền cho hóa đơn chờ thanh toán | F74: Ứng dụng đang chạy; dữ liệu mẫu đã nạp | G74: 1. Truy cập Hóa đơn → Danh sách hóa đơn hiển thị 2. Nhấn "Xác nhận đã thu tiền" tại hóa đơn ở TC002 → Trạng thái hóa đơn "Đã thanh toán" | H74: 180.000 VND | I74: Hiển thị "Thanh toán thành công", hóa đơn chuyển trạng thái đã thanh toán | J74: Thanh toán thành công, trạng thái paid | K74: Pass | N74: Nhóm kiểm thử | O74: 03/10/2026
A75: 71 | B75: UC5.2-TC002 | C75: QUẢN TRỊ VIÊN / KẾ TOÁN | D75: UC5.2 Thanh toán hóa đơn | E75: Tìm hóa đơn theo mã hóa đơn | F75: Ứng dụng đang chạy; dữ liệu mẫu đã nạp | G75: 1. Nhập mã hóa đơn vào ô tìm kiếm → Danh sách được lọc | H75: INV-2026-0020 | I75: Chỉ hiển thị 1 hóa đơn INV-2026-0020 | J75: Hiển thị đúng 1 hóa đơn | K75: Pass | N75: Nhóm kiểm thử | O75: 03/10/2026
A76: 72 | B76: UC5.2-TC003 | C76: QUẢN TRỊ VIÊN / KẾ TOÁN | D76: UC5.2 Thanh toán hóa đơn | E76: Tìm hóa đơn theo trạng thái "Quá hạn" | F76: Ứng dụng đang chạy; dữ liệu mẫu đã nạp | G76: 1. Nhập trạng thái hiển thị trên giao diện vào ô tìm kiếm → Danh sách được lọc | H76: Quá hạn | I76: Hiển thị 5 hóa đơn mẫu có trạng thái "Quá hạn" (ô tìm kiếm ghi "Tìm theo mã, khách hàng, trạng thái") | J76: Hiển thị 0 hóa đơn – bộ lọc chỉ so khớp mã trạng thái tiếng Anh (overdue), không khớp nhãn tiếng Việt | K76: Fail | L76: Thấp | M76: BUG-024 | N76: Nhóm kiểm thử | O76: 03/10/2026
A77: 73 | B77: UC7.2-TC001 | C77: QUẢN TRỊ VIÊN / KẾ TOÁN | D77: UC7.2 Báo cáo doanh thu | E77: Doanh thu trên Tổng quan khớp dữ liệu hóa đơn | F77: Ứng dụng đang chạy; dữ liệu mẫu đã nạp | G77: 1. Truy cập trang Tổng quan → Thẻ "Tổng doanh thu" hiển thị 2. So sánh với tổng hóa đơn đã thanh toán → Hai giá trị bằng nhau | I77: Tổng doanh thu hiển thị bằng tổng tiền các hóa đơn đã thanh toán | J77: Tổng doanh thu 12.905.500 VND khớp dữ liệu | K77: Pass | N77: Nhóm kiểm thử | O77: 03/10/2026
A78: 74 | B78: UC7.2-TC002 | C78: QUẢN TRỊ VIÊN / KẾ TOÁN | D78: UC7.2 Báo cáo doanh thu | E78: Thẻ "Số đơn hàng" và "Mặt hàng thuốc" khớp dữ liệu | F78: Ứng dụng đang chạy; dữ liệu mẫu đã nạp | G78: 1. Truy cập trang Tổng quan → Các thẻ thống kê hiển thị 2. So sánh với số hóa đơn và số vật tư trong CSDL → Giá trị bằng nhau | H78: ≥ 60 hóa đơn, ≥ 30 vật tư | I78: "Số đơn hàng" = tổng số hóa đơn; "Mặt hàng thuốc" = tổng số vật tư trong kho | J78: Số đơn hàng 62, mặt hàng thuốc 33 – khớp dữ liệu | K78: Pass | N78: Nhóm kiểm thử | O78: 03/10/2026

Sheet Unit test
A1: KIỂM THỬ ĐƠN VỊ (UNIT TEST)
A2: Công cụ: Mocha + tsx + node:assert. Lệnh chạy: npm run test:unit (thư mục pet-pttkpm).
A4: STT | B4: Mã UT | C4: File test | D4: Đối tượng được test | E4: Nội dung kiểm tra (kết quả mong đợi) | F4: Kết quả thực tế | G4: Trạng thái | H4: Mã lỗi | I4: Người test | J4: Ngày test
A5: 1 | B5: UT-SCH-01 | C5: tests/unit/schema.test.ts | D5: shared/schema.ts – insertCustomerSchema | E5: chấp nhận dữ liệu khách hàng hợp lệ và gán isActive mặc định = true | F5: Đúng như mong đợi | G5: Pass | I5: Nhóm kiểm thử | J5: 03/10/2026
A6: 2 | B6: UT-SCH-02 | C6: tests/unit/schema.test.ts | D6: shared/schema.ts – insertCustomerSchema | E6: từ chối email sai định dạng | F6: Đúng như mong đợi | G6: Pass | I6: Nhóm kiểm thử | J6: 03/10/2026
A7: 3 | B7: UT-SCH-03 | C7: tests/unit/schema.test.ts | D7: shared/schema.ts – insertCustomerSchema | E7: từ chối họ tên rỗng | F7: Đúng như mong đợi | G7: Pass | I7: Nhóm kiểm thử | J7: 03/10/2026
A8: 4 | B8: UT-SCH-04 | C8: tests/unit/schema.test.ts | D8: shared/schema.ts – insertCustomerSchema | E8: chấp nhận địa chỉ rỗng vì đây là trường không bắt buộc | F8: address = "" bị từ chối: String must contain at least 1 character(s) | G8: Fail | H8: BUG-002 | I8: Nhóm kiểm thử | J8: 03/10/2026
A9: 5 | B9: UT-SCH-05 | C9: tests/unit/schema.test.ts | D9: shared/schema.ts – insertCustomerSchema | E9: từ chối số điện thoại không đủ 10 chữ số (quy tắc nghiệp vụ UC1.1) | F9: Schema phía server chấp nhận SĐT "123" | G9: Fail | H9: BUG-018 | I9: Nhóm kiểm thử | J9: 03/10/2026
A10: 6 | B10: UT-SCH-06 | C10: tests/unit/schema.test.ts | D10: shared/schema.ts – insertPetSchema | E10: chuyển cân nặng kiểu số sang chuỗi (decimal) | F10: Đúng như mong đợi | G10: Pass | I10: Nhóm kiểm thử | J10: 03/10/2026
A11: 7 | B11: UT-SCH-07 | C11: tests/unit/schema.test.ts | D11: shared/schema.ts – insertPetSchema | E11: từ chối tuổi âm | F11: Đúng như mong đợi | G11: Pass | I11: Nhóm kiểm thử | J11: 03/10/2026
A12: 8 | B12: UT-SCH-08 | C12: tests/unit/schema.test.ts | D12: shared/schema.ts – insertPetSchema | E12: từ chối thú cưng thiếu loài | F12: Đúng như mong đợi | G12: Pass | I12: Nhóm kiểm thử | J12: 03/10/2026
A13: 9 | B13: UT-SCH-09 | C13: tests/unit/schema.test.ts | D13: shared/schema.ts – insertAppointmentSchema | E13: chuyển chuỗi ngày giờ thành đối tượng Date, trạng thái mặc định pending | F13: Đúng như mong đợi | G13: Pass | I13: Nhóm kiểm thử | J13: 03/10/2026
A14: 10 | B14: UT-SCH-10 | C14: tests/unit/schema.test.ts | D14: shared/schema.ts – insertAppointmentSchema | E14: từ chối trạng thái không thuộc danh sách cho phép | F14: Đúng như mong đợi | G14: Pass | I14: Nhóm kiểm thử | J14: 03/10/2026
A15: 11 | B15: UT-SCH-11 | C15: tests/unit/schema.test.ts | D15: shared/schema.ts – insertAppointmentSchema | E15: từ chối ngày giờ không hợp lệ | F15: Đúng như mong đợi | G15: Pass | I15: Nhóm kiểm thử | J15: 03/10/2026
A16: 12 | B16: UT-SCH-12 | C16: tests/unit/schema.test.ts | D16: shared/schema.ts – insertInventorySchema | E16: từ chối vật tư có tồn kho âm | F16: Đúng như mong đợi | G16: Pass | I16: Nhóm kiểm thử | J16: 03/10/2026
A17: 13 | B17: UT-SCH-13 | C17: tests/unit/schema.test.ts | D17: shared/schema.ts – insertStockBatchSchema | E17: từ chối lô hàng có số lượng 0 | F17: Đúng như mong đợi | G17: Pass | I17: Nhóm kiểm thử | J17: 03/10/2026
A18: 14 | B18: UT-SCH-14 | C18: tests/unit/schema.test.ts | D18: shared/schema.ts – insertInvoiceItemSchema | E18: từ chối dòng hóa đơn có số lượng 0 | F18: Đúng như mong đợi | G18: Pass | I18: Nhóm kiểm thử | J18: 03/10/2026
A19: 15 | B19: UT-SCH-15 | C19: tests/unit/schema.test.ts | D19: shared/schema.ts – insertPaymentSchema | E19: chỉ chấp nhận phương thức thanh toán cash, card, bank_transfer, e_wallet | F19: Đúng như mong đợi | G19: Pass | I19: Nhóm kiểm thử | J19: 03/10/2026
A20: 16 | B20: UT-SCH-16 | C20: tests/unit/schema.test.ts | D20: shared/schema.ts – insertDoctorShiftSchema | E20: từ chối ca trực có giờ kết thúc trước giờ bắt đầu | F20: Schema chấp nhận ca 17:00 – 13:00 | G20: Fail | H20: BUG-012 | I20: Nhóm kiểm thử | J20: 03/10/2026
A21: 17 | B21: UT-STO-01 | C21: tests/unit/storage.test.ts | D21: server/storage.ts – createAppointment() | E21: tạo lịch hẹn hợp lệ với trạng thái mặc định pending | F21: Đúng như mong đợi | G21: Pass | I21: Nhóm kiểm thử | J21: 03/10/2026
A22: 18 | B22: UT-STO-02 | C22: tests/unit/storage.test.ts | D22: server/storage.ts – createAppointment() | E22: từ chối lịch hẹn trùng khung giờ của bác sĩ | F22: Đúng như mong đợi | G22: Pass | I22: Nhóm kiểm thử | J22: 03/10/2026
A23: 19 | B23: UT-STO-03 | C23: tests/unit/storage.test.ts | D23: server/storage.ts – createAppointment() | E23: từ chối lịch hẹn trùng khung giờ của thú cưng | F23: Đúng như mong đợi | G23: Pass | I23: Nhóm kiểm thử | J23: 03/10/2026
A24: 20 | B24: UT-STO-04 | C24: tests/unit/storage.test.ts | D24: server/storage.ts – deleteAppointment() | E24: hủy lịch hẹn là xóa mềm (status = cancelled), khung giờ được giải phóng | F24: Đúng như mong đợi | G24: Pass | I24: Nhóm kiểm thử | J24: 03/10/2026
A25: 21 | B25: UT-STO-05 | C25: tests/unit/storage.test.ts | D25: server/storage.ts – createAppointment() | E25: từ chối lịch hẹn có ngày trong quá khứ | F25: Lịch hẹn trong quá khứ vẫn được tạo | G25: Fail | H25: BUG-010 | I25: Nhóm kiểm thử | J25: 03/10/2026
A26: 22 | B26: UT-STO-06 | C26: tests/unit/storage.test.ts | D26: server/storage.ts – updateInventoryStock() | E26: điều chỉnh tồn kho cộng/trừ đúng số lượng | F26: Đúng như mong đợi | G26: Pass | I26: Nhóm kiểm thử | J26: 03/10/2026
A27: 23 | B27: UT-STO-07 | C27: tests/unit/storage.test.ts | D27: server/storage.ts – updateInventoryStock() | E27: từ chối điều chỉnh làm tồn kho âm | F27: Đúng như mong đợi | G27: Pass | I27: Nhóm kiểm thử | J27: 03/10/2026
A28: 24 | B28: UT-STO-08 | C28: tests/unit/storage.test.ts | D28: server/storage.ts – createInvoiceItem() | E28: thêm dòng hóa đơn tự trừ tồn kho và cập nhật tổng tiền hóa đơn | F28: Đúng như mong đợi | G28: Pass | I28: Nhóm kiểm thử | J28: 03/10/2026
A29: 25 | B29: UT-STO-09 | C29: tests/unit/storage.test.ts | D29: server/storage.ts – createInvoiceItem() | E29: từ chối dòng hóa đơn vượt tồn kho, không thay đổi tồn kho (transaction rollback) | F29: Đúng như mong đợi | G29: Pass | I29: Nhóm kiểm thử | J29: 03/10/2026
A30: 26 | B30: UT-STO-10 | C30: tests/unit/storage.test.ts | D30: server/storage.ts – getLowStockItems() | E30: vật tư có tồn kho <= tồn tối thiểu nằm trong danh sách sắp hết | F30: Đúng như mong đợi | G30: Pass | I30: Nhóm kiểm thử | J30: 03/10/2026
A31: 27 | B31: UT-STO-11 | C31: tests/unit/storage.test.ts | D31: server/storage.ts – getExpiringBatches() | E31: lô hàng hết hạn trong 30 ngày nằm trong danh sách sắp hết hạn | F31: Đúng như mong đợi | G31: Pass | I31: Nhóm kiểm thử | J31: 03/10/2026
A32: 28 | B32: UT-STO-12 | C32: tests/unit/storage.test.ts | D32: server/storage.ts – createStockBatch() | E32: nhập lô hàng mới làm tăng tồn kho của vật tư (R4.1) | F32: Tồn kho không đổi (2 → 2) sau khi nhập lô 20 | G32: Fail | H32: BUG-019 | I32: Nhóm kiểm thử | J32: 03/10/2026
A33: 29 | B33: UT-STO-13 | C33: tests/unit/storage.test.ts | D33: server/storage.ts – createCustomer() | E33: từ chối tạo khách hàng trùng số điện thoại | F33: Khách hàng trùng SĐT vẫn được tạo | G33: Fail | H33: BUG-007 | I33: Nhóm kiểm thử | J33: 03/10/2026
A34: 30 | B34: UT-STO-14 | C34: tests/unit/storage.test.ts | D34: server/storage.ts – getCustomers() | E34: tìm kiếm khách hàng theo số điện thoại | F34: Đúng như mong đợi | G34: Pass | I34: Nhóm kiểm thử | J34: 03/10/2026

Sheet TC phi chức năng
A1: TEST CASE KIỂM THỬ PHI CHỨC NĂNG
A2: Tải & hiệu năng, chịu tải: autocannon. Toàn vẹn dữ liệu: Mocha + mysql2. Tin cậy & phục hồi: Mocha + autocannon.
A4: STT | B4: Test Case ID | C4: Loại kiểm thử | D4: Mô tả | E4: Cách thực hiện | F4: Công cụ | G4: Tiêu chí đạt | H4: Kết quả đo được | I4: Trạng thái | J4: Mức độ lỗi | K4: Mã lỗi | L4: Người test | M4: Ngày test
A5: 1 | B5: LOAD-TC001 | C5: Tải & hiệu năng | D5: Trang Tổng quan – GET /api/dashboard/stats | E5: autocannon: 200 kết nối đồng thời trong 30.17 giây | F5: autocannon + Mocha | G5: p99 ≤ 3.000 ms; tỷ lệ lỗi 0% | H5: 71.419 yêu cầu, 2381 req/s; p50 83 ms, p99 106 ms; lỗi 0% | I5: Pass | L5: Nhóm kiểm thử | M5: 03/10/2026
A6: 2 | B6: LOAD-TC002 | C6: Tải & hiệu năng | D6: Danh sách khách hàng – GET /api/customers | E6: autocannon: 200 kết nối đồng thời trong 30.17 giây | F6: autocannon + Mocha | G6: p99 ≤ 3.000 ms; tỷ lệ lỗi 0% | H6: 69.616 yêu cầu, 2321 req/s; p50 84 ms, p99 118 ms; lỗi 0% | I6: Pass | L6: Nhóm kiểm thử | M6: 03/10/2026
A7: 3 | B7: LOAD-TC003 | C7: Tải & hiệu năng | D7: Danh sách lịch hẹn – GET /api/appointments | E7: autocannon: 200 kết nối đồng thời trong 30.11 giây | F7: autocannon + Mocha | G7: p99 ≤ 3.000 ms; tỷ lệ lỗi 0% | H7: 62.641 yêu cầu, 2088 req/s; p50 90 ms, p99 148 ms; lỗi 0% | I7: Pass | L7: Nhóm kiểm thử | M7: 03/10/2026
A8: 4 | B8: LOAD-TC004 | C8: Tải & hiệu năng | D8: Kho thuốc – GET /api/inventory | E8: autocannon: 200 kết nối đồng thời trong 30.06 giây | F8: autocannon + Mocha | G8: p99 ≤ 3.000 ms; tỷ lệ lỗi 0% | H8: 70.986 yêu cầu, 2367 req/s; p50 83 ms, p99 124 ms; lỗi 0% | I8: Pass | L8: Nhóm kiểm thử | M8: 03/10/2026
A9: 5 | B9: LOAD-TC005 | C9: Tải & hiệu năng | D9: Kịch bản hỗn hợp (đọc nhiều màn hình) | E9: autocannon: 200 kết nối đồng thời trong 30.1 giây | F9: autocannon + Mocha | G9: p99 ≤ 3.000 ms; tỷ lệ lỗi 0% | H9: 15.558 yêu cầu, 519 req/s; p50 381 ms, p99 637 ms; lỗi 0% | I9: Pass | L9: Nhóm kiểm thử | M9: 03/10/2026
A10: 6 | B10: LOAD-TC006 | C10: Tải & hiệu năng | D10: Tải ghi – POST /api/customers (lễ tân tạo hồ sơ) | E10: autocannon: 200 kết nối đồng thời trong 30.07 giây | F10: autocannon + Mocha | G10: p99 ≤ 3.000 ms; tỷ lệ lỗi 0% | H10: 21.135 yêu cầu, 705 req/s; p50 276 ms, p99 346 ms; lỗi 0% | I10: Pass | L10: Nhóm kiểm thử | M10: 03/10/2026
A11: 7 | B11: PERF-TC001 | C11: Tải & hiệu năng | D11: Tìm kiếm khách hàng trên 10.030 bản ghi – 1 người dùng | E11: Nạp 10.000 khách hàng; 50 lượt tìm theo tên, SĐT, email | F11: autocannon + Mocha | G11: p95 ≤ 2.000 ms (đặc tả mục 1.3) | H11: TB 26 ms, p95 36 ms, max 99 ms | I11: Pass | L11: Nhóm kiểm thử | M11: 03/10/2026
A12: 8 | B12: PERF-TC002 | C12: Tải & hiệu năng | D12: Tìm kiếm trên 10.000 bản ghi – 50 người dùng đồng thời | E12: autocannon: 50 kết nối trong 20 giây | F12: autocannon + Mocha | G12: p99 ≤ 2.000 ms; lỗi 0% | H12: 2369 req/s; p50 20 ms, p99 33 ms; lỗi 0% | I12: Pass | L12: Nhóm kiểm thử | M12: 03/10/2026
A13: 9 | B13: STRESS-TC001 | C13: Chịu tải | D13: Tăng dần tải để tìm ngưỡng quá tải | E13: Kịch bản hỗn hợp, 50 → 100 → 200 → 400 → 800 → 1200 → 1600 kết nối, 15 giây/mức | F13: autocannon + Mocha | G13: Không quá tải ở mức ≤ 200 kết nối (yêu cầu đặc tả) | H13: Đạt yêu cầu tới 400 kết nối; quá tải từ 800 kết nối (p99 3.717 ms); lỗi cao nhất 27.39% | I13: Pass | L13: Nhóm kiểm thử | M13: 03/10/2026
A14: 10 | B14: STRESS-TC002 | C14: Chịu tải | D14: Máy chủ không bị sập khi quá tải | E14: Gọi API ngay sau mức tải cao nhất | F14: autocannon + Mocha | G14: HTTP 200 | H14: HTTP 200, tiến trình vẫn chạy | I14: Pass | L14: Nhóm kiểm thử | M14: 03/10/2026
A15: 11 | B15: STRESS-TC003 | C15: Chịu tải | D15: Hồi phục sau quá tải | E15: Giảm về 50 kết nối trong 10 giây | F15: autocannon + Mocha | G15: p99 ≤ 3.000 ms; lỗi 0% | H15: p99 316 ms; lỗi 0% | I15: Pass | L15: Nhóm kiểm thử | M15: 03/10/2026
A16: 12 | B16: DI-TC001 | C16: Toàn vẹn dữ liệu | D16: 20 giao dịch bán đồng thời trên vật tư tồn kho 10 | E16: Gửi đồng thời 20 yêu cầu POST /api/invoice-items, mỗi yêu cầu 1 hộp | F16: Mocha + mysql2 | G16: Đúng 10 giao dịch thành công; tồn kho = 0; không bán vượt | H16: Số đã bán (20) + tồn (8) ≠ 10 – bán vượt tồn kho | I16: Fail | J16: Cao | K16: BUG-005 | L16: Nhóm kiểm thử | M16: 03/10/2026
A17: 13 | B17: DI-TC002 | C17: Toàn vẹn dữ liệu | D17: 10 yêu cầu đặt cùng bác sĩ, cùng khung giờ đồng thời | E17: Gửi đồng thời 10 yêu cầu POST /api/appointments | F17: Mocha + mysql2 | G17: Chỉ 1 lịch hẹn được tạo | H17: Có 10 lịch hẹn cùng bác sĩ, cùng khung giờ | I17: Fail | J17: Cao | K17: BUG-006 | L17: Nhóm kiểm thử | M17: 03/10/2026
A18: 14 | B18: DI-TC003 | C18: Toàn vẹn dữ liệu | D18: Tổng tiền hóa đơn khớp các dòng hóa đơn | E18: Truy vấn SQL đối chiếu toàn bộ hóa đơn | F18: Mocha + mysql2 | G18: 0 hóa đơn lệch | H18: Đạt | I18: Pass | L18: Nhóm kiểm thử | M18: 03/10/2026
A19: 15 | B19: DI-TC004 | C19: Toàn vẹn dữ liệu | D19: Không có tồn kho âm | E19: Truy vấn SQL bảng inventory | F19: Mocha + mysql2 | G19: 0 bản ghi stock < 0 | H19: Đạt | I19: Pass | L19: Nhóm kiểm thử | M19: 03/10/2026
A20: 16 | B20: DI-TC005 | C20: Toàn vẹn dữ liệu | D20: Ràng buộc khóa ngoại thú cưng – khách hàng | E20: Tạo thú cưng với customerId không tồn tại | F20: Mocha + mysql2 | G20: HTTP 400; 0 thú cưng mồ côi | H20: Đạt | I20: Pass | L20: Nhóm kiểm thử | M20: 03/10/2026
A21: 17 | B21: DI-TC006 | C21: Toàn vẹn dữ liệu | D21: Hóa đơn chuyển "Đã thanh toán" khi thu đủ qua nhiều lần | E21: Hóa đơn 300.000đ, thu 100.000đ rồi 200.000đ | F21: Mocha + mysql2 | G21: Sau lần 1: pending; sau lần 2: paid | H21: Đã thu đủ 300.000đ qua 2 lần nhưng hóa đơn vẫn "pending" | I21: Fail | J21: Trung bình | K21: BUG-016 | L21: Nhóm kiểm thử | M21: 03/10/2026
A22: 18 | B22: DI-TC007 | C22: Toàn vẹn dữ liệu | D22: Từ chối thanh toán vượt số tiền hóa đơn | E22: Thu 5.000.000đ cho hóa đơn 200.000đ | F22: Mocha + mysql2 | G22: HTTP 400 | H22: Thanh toán 5.000.000đ cho hóa đơn 200.000đ được chấp nhận (HTTP 201) | I22: Fail | J22: Trung bình | K22: BUG-017 | L22: Nhóm kiểm thử | M22: 03/10/2026
A23: 19 | B23: DI-TC008 | C23: Toàn vẹn dữ liệu | D23: Tiếng Việt, emoji, ký tự HTML được lưu nguyên vẹn | E23: Tạo khách hàng tên có dấu, emoji 🐶, ký tự <b>&'" rồi đọc lại | F23: Mocha + mysql2 | G23: Dữ liệu đọc lại giống hệt | H23: Đạt | I23: Pass | L23: Nhóm kiểm thử | M23: 03/10/2026
A24: 20 | B24: DI-TC009 | C24: Toàn vẹn dữ liệu | D24: Chuỗi SQL Injection trong ô tìm kiếm | E24: 4 chuỗi tấn công (' OR '1'='1, DROP TABLE…) | F24: Mocha + mysql2 | G24: HTTP 200, 0 kết quả, số bản ghi không đổi | H24: Đạt | I24: Pass | L24: Nhóm kiểm thử | M24: 03/10/2026
A25: 21 | B25: DI-TC010 | C25: Toàn vẹn dữ liệu | D25: Họ tên 5.000 ký tự | E25: POST /api/customers với tên 5.000 ký tự | F25: Mocha + mysql2 | G25: Từ chối hoặc lưu nguyên vẹn, không lỗi 5xx | H25: Đạt | I25: Pass | L25: Nhóm kiểm thử | M25: 03/10/2026
A26: 22 | B26: DI-TC011 | C26: Toàn vẹn dữ liệu | D26: Cập nhật một trường không làm mất trường khác | E26: PATCH địa chỉ, đọc lại hồ sơ | F26: Mocha + mysql2 | G26: Các trường khác giữ nguyên | H26: Đạt | I26: Pass | L26: Nhóm kiểm thử | M26: 03/10/2026
A27: 23 | B27: REL-TC001 | C27: Tin cậy & phục hồi | D27: Yêu cầu sai định dạng JSON | E27: POST /api/customers với body hỏng | F27: Mocha + autocannon | G27: HTTP 4xx, ứng dụng vẫn chạy | H27: HTTP 400, ứng dụng vẫn chạy | I27: Pass | L27: Nhóm kiểm thử | M27: 03/10/2026
A28: 24 | B28: REL-TC002 | C28: Tin cậy & phục hồi | D28: Mất kết nối CSDL khi đang chạy | E28: Dừng MySQL, gọi API | F28: Mocha + autocannon | G28: HTTP 5xx có kiểm soát, ứng dụng không sập | H28: HTTP 500; ứng dụng vẫn chạy | I28: Pass | L28: Nhóm kiểm thử | M28: 03/10/2026
A29: 25 | B29: REL-TC003 | C29: Tin cậy & phục hồi | D29: Tự phục hồi khi CSDL hoạt động lại | E29: Khởi động lại MySQL, không khởi động lại ứng dụng | F29: Mocha + autocannon | G29: API trở lại bình thường ≤ 30 giây | H29: Phục hồi sau 1.056 ms | I29: Pass | L29: Nhóm kiểm thử | M29: 03/10/2026
A30: 26 | B30: REL-TC004 | C30: Tin cậy & phục hồi | D30: Dữ liệu bền vững khi ứng dụng bị tắt đột ngột | E30: Tạo hồ sơ, kill tiến trình, khởi động lại, đọc hồ sơ | F30: Mocha + autocannon | G30: Hồ sơ còn nguyên | H30: Hồ sơ còn nguyên | I30: Pass | L30: Nhóm kiểm thử | M30: 03/10/2026
A31: 27 | B31: REL-TC005 | C31: Tin cậy & phục hồi | D31: Thời gian khởi động lại ứng dụng | E31: Đo từ lúc khởi chạy tới khi API trả 200 | F31: Mocha + autocannon | G31: ≤ 10 giây | H31: 834 ms | I31: Pass | L31: Nhóm kiểm thử | M31: 03/10/2026
A32: 28 | B32: REL-TC006 | C32: Tin cậy & phục hồi | D32: Chạy tải liên tục 180 giây | E32: autocannon: 50 kết nối, 4 API đọc | F32: Mocha + autocannon | G32: Lỗi 0%; p99 ≤ 3.000 ms; RAM không tăng liên tục | H32: 61.913 yêu cầu; p99 395 ms; lỗi 0%; RAM 219 → 335 → 324 MB | I32: Pass | L32: Nhóm kiểm thử | M32: 03/10/2026

Sheet Danh sách lỗi
A1: DANH SÁCH LỖI (BUG REPORT)
A2: Mỗi lỗi gắn với test case phát hiện ra nó. Trạng thái xử lý cập nhật khi nhóm phát triển sửa lỗi.
A4: Mã lỗi | B4: Test case | C4: Loại | D4: Tiêu đề lỗi | E4: Mức độ | F4: Ưu tiên | G4: Bước tái hiện | H4: Kết quả mong đợi | I4: Kết quả thực tế | J4: Vị trí nghi vấn trong mã nguồn | K4: Trạng thái xử lý | L4: Người phát hiện | M4: Ngày phát hiện
A5: BUG-001 | B5: SYS-TC004 | C5: Chức năng | D5: Chưa có đăng nhập và phân quyền RBAC; mọi người truy cập URL đều thao tác được dữ liệu | E5: Cao | F5: P1 – Gấp | G5: 1. Mở trình duyệt mới (chưa đăng nhập) 2. Truy cập trực tiếp trang Khách hàng (/customers) | H5: Hệ thống yêu cầu đăng nhập, không cho xem dữ liệu khách hàng | I5: Không có trang đăng nhập – truy cập thẳng được danh sách khách hàng | J5: client/src/App.tsx, server/routes.ts (không có middleware xác thực) | K5: Mới (New) | L5: Nhóm kiểm thử | M5: 03/10/2026
A6: BUG-002 | B6: UC1.1-TC010 | C6: Chức năng | D6: Bỏ trống ô Địa chỉ (không bắt buộc) thì không thêm được khách hàng; thông báo lỗi là chuỗi JSON | E6: Cao | F6: P1 – Gấp | G6: 1. Chọn "Thêm khách hàng" 2. Nhập Họ tên, Email, SĐT hợp lệ (Khách Không Địa Chỉ / kdc106379@test.vn / 0910637922) 3. Bỏ trống Địa chỉ 4. Nhấn "Lưu khách hàng" | H6: Hiển thị "Thêm khách hàng thành công" (Địa chỉ không có dấu * nên không bắt buộc) | I6: Hiển thị "Không thể thêm khách hàng" kèm lỗi JSON: "String must contain at least 1 character(s)", path ["address"] | J6: AddCustomerDialog.tsx gửi address = ""; shared/schema.ts: nullableString = z.string().min(1) | K6: Mới (New) | L6: Nhóm kiểm thử | M6: 03/10/2026
A7: BUG-003 | B7: UC1.5-TC001 | C7: Chức năng | D7: Ô tìm kiếm khách hàng mất focus sau ký tự đầu, không gõ tiếp được | E7: Cao | F7: P1 – Gấp | G7: 1. Nhập tên vào ô tìm kiếm (Trần Lan) | H7: Chỉ hiển thị khách hàng "Trần Lan" | I7: Ô tìm kiếm mất focus sau ký tự đầu – chỉ nhận "T", danh sách lọc sai | J7: CustomerList.tsx:70 – return sớm khi isLoading làm ô tìm kiếm bị gỡ khỏi DOM | K7: Mới (New) | L7: Nhóm kiểm thử | M7: 03/10/2026
A8: BUG-004 | B8: UC1.5-TC002 | C8: Chức năng | D8: Như UC1.5-TC001 khi tìm theo số điện thoại | E8: Cao | F8: P1 – Gấp | G8: 1. Nhập SĐT vào ô tìm kiếm (0911000003) | H8: Hiển thị khách hàng "Phạm Tuấn" | I8: Ô tìm kiếm mất focus sau ký tự đầu – chỉ nhận "0", danh sách lọc sai | J8: CustomerList.tsx:70 | K8: Mới (New) | L8: Nhóm kiểm thử | M8: 03/10/2026
A9: BUG-005 | B9: DI-TC001 | C9: Toàn vẹn dữ liệu | D9: Bán đồng thời: tồn kho bị ghi đè (lost update), bán vượt số lượng thực có | E9: Cao | F9: P1 – Gấp | G9: Gửi đồng thời 20 yêu cầu POST /api/invoice-items, mỗi yêu cầu 1 hộp | H9: Đúng 10 giao dịch thành công; tồn kho = 0; không bán vượt | I9: Số đã bán (20) + tồn (8) ≠ 10 – bán vượt tồn kho | J9: server/storage.ts – createInvoiceItem(): đọc tồn kho không khóa (thiếu SELECT … FOR UPDATE hoặc UPDATE có điều kiện) | K9: Mới (New) | L9: Nhóm kiểm thử | M9: 03/10/2026
A10: BUG-006 | B10: DI-TC002 | C10: Toàn vẹn dữ liệu | D10: Đặt lịch đồng thời: nhiều lịch trùng bác sĩ, trùng giờ cùng được tạo | E10: Cao | F10: P1 – Gấp | G10: Gửi đồng thời 10 yêu cầu POST /api/appointments | H10: Chỉ 1 lịch hẹn được tạo | I10: Có 10 lịch hẹn cùng bác sĩ, cùng khung giờ | J10: server/storage.ts – createAppointment(): kiểm tra rồi mới chèn, không khóa và không có ràng buộc UNIQUE | K10: Mới (New) | L10: Nhóm kiểm thử | M10: 03/10/2026
A11: BUG-007 | B11: UC1.1-TC008 | C11: Chức năng | D11: Không kiểm tra trùng số điện thoại | E11: Trung bình | F11: P2 – Cao | G11: 1. Chọn "Thêm khách hàng" 2. Nhập Họ tên, Email mới, Địa chỉ (Khách Trùng SĐT / trungsdt@test.vn / Hà Nội) 3. Nhập SĐT đã tồn tại (của Nguyễn Huy) (0911000001) 4. Nhấn "Lưu khách hàng" | H11: Hiển thị lỗi số điện thoại đã tồn tại, không tạo khách hàng (quy tắc nghiệp vụ UC1.1) | I11: Hệ thống vẫn lưu khách hàng có SĐT trùng 0911000001 | J11: server/storage.ts – createCustomer() | K11: Mới (New) | L11: Nhóm kiểm thử | M11: 03/10/2026
A12: BUG-008 | B12: UC1.1-TC009 | C12: Chức năng | D12: Không kiểm tra trùng email | E12: Trung bình | F12: P2 – Cao | G12: 1. Chọn "Thêm khách hàng" 2. Nhập Họ tên, SĐT mới, Địa chỉ (Khách Trùng Email / 0977000999 / Hà Nội) 3. Nhập Email đã tồn tại (owner.huy@example.com) 4. Nhấn "Lưu khách hàng" | H12: Hiển thị lỗi email đã tồn tại, không tạo khách hàng | I12: Hệ thống vẫn lưu khách hàng có email trùng | J12: server/storage.ts – createCustomer() | K12: Mới (New) | L12: Nhóm kiểm thử | M12: 03/10/2026
A13: BUG-009 | B13: UC1.2-TC004 | C13: Chức năng | D13: Không kiểm tra trùng mã microchip | E13: Trung bình | F13: P2 – Cao | G13: 1. Nhấn "Thêm thú cưng" 2. Nhập Tên, chọn Loài (Mực / Chó) 3. Nhập microchip đã dùng ở TC003 (MC-106379) 4. Nhấn "Lưu thú cưng" | H13: Hiển thị "Microchip đã tồn tại, vui lòng kiểm tra lại." (luồng thay thế UC1.2) | I13: Hệ thống vẫn lưu thú cưng có microchip trùng | J13: server/storage.ts – createPet() | K13: Mới (New) | L13: Nhóm kiểm thử | M13: 03/10/2026
A14: BUG-010 | B14: UC2.1-TC005 | C14: Chức năng | D14: Cho phép đặt lịch hẹn trong quá khứ | E14: Trung bình | F14: P2 – Cao | G14: 1. Chọn "Tạo lịch hẹn" 2. Chọn khách hàng, thú cưng, dịch vụ hợp lệ (Nguyễn Huy / Bông 106379) 3. Chọn ngày hôm qua (2026-10-02 10:00) 4. Nhấn lưu | H14: Hệ thống từ chối lịch hẹn trong quá khứ | I14: Hệ thống vẫn tạo lịch hẹn ngày 2026-10-02 | J14: server/storage.ts – createAppointment() | K14: Mới (New) | L14: Nhóm kiểm thử | M14: 03/10/2026
A15: BUG-011 | B15: UC2.2-TC004 | C15: Chức năng | D15: Cho phép hủy lịch khi còn dưới 1 tiếng (trái R2.2) | E15: Trung bình | F15: P2 – Cao | G15: 1. Có lịch hẹn bắt đầu sau 30 phút (Giờ hiện tại + 30 phút) 2. Nhấn "Hủy lịch" | H15: Hệ thống từ chối – chỉ được hủy trước giờ hẹn ít nhất 1 tiếng (R2.2) | I15: Lịch hẹn vẫn bị hủy dù chỉ còn 30 phút | J15: server/storage.ts – deleteAppointment() | K15: Mới (New) | L15: Nhóm kiểm thử | M15: 03/10/2026
... A28: BUG-024 | B28: UC5.2-TC003 | C28: Chức năng | D28: Tìm hóa đơn theo trạng thái hiển thị ("Quá hạn", "Đã hủy"…) không ra kết quả | E28: Thấp | F28: P3 – Bình thường | G28: 1. Nhập trạng thái hiển thị trên giao diện vào ô tìm kiếm (Quá hạn) | H28: Hiển thị 5 hóa đơn mẫu có trạng thái "Quá hạn" (ô tìm kiếm ghi "Tìm theo mã, khách hàng, trạng thái") | I28: Hiển thị 0 hóa đơn – bộ lọc chỉ so khớp mã trạng thái tiếng Anh (overdue), không khớp nhãn tiếng Việt | J28: InvoicesPage.tsx – bộ lọc so khớp inv.status (overdue, paid…) thay vì nhãn tiếng Việt | K28: Mới (New) | L28: Nhóm kiểm thử | M28: 03/10/2026
